<?xml version="1.0" encoding="ISO-8859-1"?>
	<Document>
		<totalPresent>5595</totalPresent>
		<totalLibre>4340</totalLibre>
		<lastUpdate>sam., 05 janv. 2019 12:24:01 +0100</lastUpdate>
		<Quartier>
			<nomQuartier>Fontvieille</nomQuartier>
			<totalLibresQuartier>1645</totalLibresQuartier>
			<totalPresentsQuartier>1117</totalPresentsQuartier>
			<totalPresentsHorairesQuartier>566</totalPresentsHorairesQuartier>
			<totalPresentsAbonnesQuartier>551</totalPresentsAbonnesQuartier>
			<Parc>
				<numParc>124</numParc>
				<libelleParc>ECOLES RDC</libelleParc>
				<statusParc>LIBRE</statusParc>
				<placesLibresParc>56</placesLibresParc>
				<placesLibresUpdate>2019-01-05 12:23:46.195759</placesLibresUpdate>
				<presents>
					<presentsUpdate>2019-01-05 12:23:47.182492</presentsUpdate>
					<presentsTotal>11</presentsTotal>
					<presentsAbonnes>7</presentsAbonnes>
					<presentsHoraires>4</presentsHoraires>
				</presents>
			</Parc>
			<Parc>
				<numParc>13</numParc>
				<libelleParc>PAPALINS</libelleParc>
				<statusParc>LIBRE</statusParc>
				<placesLibresParc>203</placesLibresParc>
				<placesLibresUpdate>2019-01-05 12:23:45.92525</placesLibresUpdate>
				<presents>
					<presentsUpdate>2019-01-05 12:23:46.575783</presentsUpdate>
					<presentsTotal>82</presentsTotal>
					<presentsAbonnes>55</presentsAbonnes>
					<presentsHoraires>27</presentsHoraires>
				</presents>
			</Parc>
			<Parc>
				<numParc>14</numParc>
				<libelleParc>STADE</libelleParc>
				<statusParc>LIBRE</statusParc>
				<placesLibresParc>892</placesLibresParc>
				<placesLibresUpdate>2019-01-05 12:23:45.933838</placesLibresUpdate>
				<presents>
					<presentsUpdate>2019-01-05 12:23:46.986699</presentsUpdate>
					<presentsTotal>221</presentsTotal>
					<presentsAbonnes>181</presentsAbonnes>
					<presentsHoraires>40</presentsHoraires>
				</presents>
			</Parc>
			<Parc>
				<numParc>21</numParc>
				<libelleParc>PORT</libelleParc>
				<statusParc>LIBRE</statusParc>
				<placesLibresParc>54</placesLibresParc>
				<placesLibresUpdate>2019-01-05 12:23:45.975527</placesLibresUpdate>
				<presents>
					<presentsUpdate>2019-01-05 12:23:47.013634</presentsUpdate>
					<presentsTotal>82</presentsTotal>
					<presentsAbonnes>74</presentsAbonnes>
					<presentsHoraires>8</presentsHoraires>
				</presents>
			</Parc>
			<Parc>
				<numParc>24</numParc>
				<libelleParc>ECOLES</libelleParc>
				<statusParc>LIBRE</statusParc>
				<placesLibresParc>13</placesLibresParc>
				<placesLibresUpdate>2019-01-05 12:23:45.992453</placesLibresUpdate>
				<presents>
					<presentsUpdate>2019-01-05 12:23:47.02269</presentsUpdate>
					<presentsTotal>49</presentsTotal>
					<presentsAbonnes>49</presentsAbonnes>
					<presentsHoraires>0</presentsHoraires>
				</presents>
			</Parc>
			<Parc>
				<numParc>25</numParc>
				<libelleParc>ST NICOLAS</libelleParc>
				<statusParc>LIBRE</statusParc>
				<placesLibresParc>24</placesLibresParc>
				<placesLibresUpdate>2019-01-05 12:23:46.000828</placesLibresUpdate>
				<presents>
					<presentsUpdate>2019-01-05 12:23:47.031553</presentsUpdate>
					<presentsTotal>10</presentsTotal>
					<presentsAbonnes>7</presentsAbonnes>
					<presentsHoraires>3</presentsHoraires>
				</presents>
			</Parc>
			<Parc>
				<numParc>29</numParc>
				<libelleParc>HELIPORT</libelleParc>
				<statusParc>LIBRE</statusParc>
				<placesLibresParc>32</placesLibresParc>
				<placesLibresUpdate>2019-01-05 12:23:46.03439</placesLibresUpdate>
				<presents>
					<presentsUpdate>2019-01-05 12:23:47.04956</presentsUpdate>
					<presentsTotal>48</presentsTotal>
					<presentsAbonnes>29</presentsAbonnes>
					<presentsHoraires>19</presentsHoraires>
				</presents>
			</Parc>
			<Parc>
				<numParc>30</numParc>
				<libelleParc>C.C.F.</libelleParc>
				<statusParc>LIBRE</statusParc>
				<placesLibresParc>112</placesLibresParc>
				<placesLibresUpdate>2019-01-05 12:23:46.042851</placesLibresUpdate>
				<presents>
					<presentsUpdate>2019-01-05 12:23:47.058646</presentsUpdate>
					<presentsTotal>457</presentsTotal>
					<presentsAbonnes>9</presentsAbonnes>
					<presentsHoraires>448</presentsHoraires>
				</presents>
			</Parc>
			<Parc>
				<numParc>52</numParc>
				<libelleParc>ST ANTOINE</libelleParc>
				<statusParc>LIBRE</statusParc>
				<placesLibresParc>259</placesLibresParc>
				<placesLibresUpdate>2019-01-05 12:23:46.161815</placesLibresUpdate>
				<presents>
					<presentsUpdate>2019-01-05 12:23:47.106199</presentsUpdate>
					<presentsTotal>157</presentsTotal>
					<presentsAbonnes>140</presentsAbonnes>
					<presentsHoraires>17</presentsHoraires>
				</presents>
			</Parc>
		</Quartier>
		<Quartier>
			<nomQuartier>I-Cars</nomQuartier>
			<totalLibresQuartier>47</totalLibresQuartier>
			<totalPresentsQuartier>7</totalPresentsQuartier>
			<totalPresentsHorairesQuartier>3</totalPresentsHorairesQuartier>
			<totalPresentsAbonnesQuartier>4</totalPresentsAbonnesQuartier>
			<Parc>
				<numParc>104</numParc>
				<libelleParc>GRIMALDI FORUM BUS</libelleParc>
				<statusParc>LIBRE</statusParc>
				<placesLibresParc>29</placesLibresParc>
				<placesLibresUpdate>2019-01-05 12:23:46.178648</placesLibresUpdate>
				<presents>
					<presentsUpdate>2019-01-05 12:23:46.812992</presentsUpdate>
					<presentsTotal>6</presentsTotal>
					<presentsAbonnes>3</presentsAbonnes>
					<presentsHoraires>3</presentsHoraires>
				</presents>
			</Parc>
			<Parc>
				<numParc>112</numParc>
				<libelleParc>PECHEURS BUS</libelleParc>
				<statusParc>LIBRE</statusParc>
				<placesLibresParc>16</placesLibresParc>
				<placesLibresUpdate>2019-01-05 12:23:46.187358</placesLibresUpdate>
				<presents>
					<presentsUpdate>2019-01-05 12:23:47.14869</presentsUpdate>
					<presentsTotal>1</presentsTotal>
					<presentsAbonnes>1</presentsAbonnes>
					<presentsHoraires>0</presentsHoraires>
				</presents>
			</Parc>
			<Parc>
				<numParc>19</numParc>
				<libelleParc>REGULATION BUS</libelleParc>
				<statusParc>LIBRE</statusParc>
				<placesLibresParc>2</placesLibresParc>
				<placesLibresUpdate>2019-01-05 12:23:45.967152</placesLibresUpdate>
				<presents>
					<presentsUpdate>2010-04-16 09:17:37.639024</presentsUpdate>
					<presentsTotal>0</presentsTotal>
					<presentsAbonnes>Obsolete</presentsAbonnes>
					<presentsHoraires>Obsolete</presentsHoraires>
				</presents>
			</Parc>
		</Quartier>
		<Quartier>
			<nomQuartier>Jardin-Exotique</nomQuartier>
			<totalLibresQuartier>608</totalLibresQuartier>
			<totalPresentsQuartier>1137</totalPresentsQuartier>
			<totalPresentsHorairesQuartier>180</totalPresentsHorairesQuartier>
			<totalPresentsAbonnesQuartier>957</totalPresentsAbonnesQuartier>
			<Parc>
				<numParc>127</numParc>
				<libelleParc>CHPG 2 (BAS)</libelleParc>
				<statusParc>LIBRE</statusParc>
				<placesLibresParc>144</placesLibresParc>
				<placesLibresUpdate>2019-01-05 12:23:46.204214</placesLibresUpdate>
				<presents>
					<presentsUpdate>2019-01-05 12:23:46.83823</presentsUpdate>
					<presentsTotal>123</presentsTotal>
					<presentsAbonnes>0</presentsAbonnes>
					<presentsHoraires>123</presentsHoraires>
				</presents>
			</Parc>
			<Parc>
				<numParc>16</numParc>
				<libelleParc>JARDIN EXOTIQUE</libelleParc>
				<statusParc>LIBRE</statusParc>
				<placesLibresParc>86</placesLibresParc>
				<placesLibresUpdate>2019-01-05 12:23:45.950419</placesLibresUpdate>
				<presents>
					<presentsUpdate>2019-01-05 12:23:46.684951</presentsUpdate>
					<presentsTotal>251</presentsTotal>
					<presentsAbonnes>239</presentsAbonnes>
					<presentsHoraires>12</presentsHoraires>
				</presents>
			</Parc>
			<Parc>
				<numParc>27</numParc>
				<libelleParc>CHPG 1 (HAUT)</libelleParc>
				<statusParc>COMPLET</statusParc>
				<placesLibresParc>0</placesLibresParc>
				<placesLibresUpdate>2019-01-05 12:23:46.017791</placesLibresUpdate>
				<presents>
					<presentsUpdate>2019-01-05 12:23:46.710689</presentsUpdate>
					<presentsTotal>0</presentsTotal>
					<presentsAbonnes>46</presentsAbonnes>
					<presentsHoraires>0</presentsHoraires>
				</presents>
			</Parc>
			<Parc>
				<numParc>34</numParc>
				<libelleParc>GARE</libelleParc>
				<statusParc>LIBRE</statusParc>
				<placesLibresParc>223</placesLibresParc>
				<placesLibresUpdate>2019-01-05 12:23:46.076309</placesLibresUpdate>
				<presents>
					<presentsUpdate>2019-01-05 12:23:46.727686</presentsUpdate>
					<presentsTotal>441</presentsTotal>
					<presentsAbonnes>429</presentsAbonnes>
					<presentsHoraires>12</presentsHoraires>
				</presents>
			</Parc>
			<Parc>
				<numParc>45</numParc>
				<libelleParc>ATHENA</libelleParc>
				<statusParc>COMPLET</statusParc>
				<placesLibresParc>0</placesLibresParc>
				<placesLibresUpdate>2019-01-05 12:23:46.144674</placesLibresUpdate>
				<presents>
					<presentsUpdate>2019-01-05 12:23:46.787409</presentsUpdate>
					<presentsTotal>0</presentsTotal>
					<presentsAbonnes>14</presentsAbonnes>
					<presentsHoraires>0</presentsHoraires>
				</presents>
			</Parc>
			<Parc>
				<numParc>46</numParc>
				<libelleParc>DES OLIVIERS</libelleParc>
				<statusParc>LIBRE</statusParc>
				<placesLibresParc>23</placesLibresParc>
				<placesLibresUpdate>2019-01-05 12:23:46.15333</placesLibresUpdate>
				<presents>
					<presentsUpdate>2019-01-05 12:23:46.79601</presentsUpdate>
					<presentsTotal>4</presentsTotal>
					<presentsAbonnes>0</presentsAbonnes>
					<presentsHoraires>4</presentsHoraires>
				</presents>
			</Parc>
			<Parc>
				<numParc>60</numParc>
				<libelleParc>ENGELIN</libelleParc>
				<statusParc>LIBRE</statusParc>
				<placesLibresParc>88</placesLibresParc>
				<placesLibresUpdate>2019-01-05 12:23:46.170149</placesLibresUpdate>
				<presents>
					<presentsUpdate>2019-01-05 12:23:46.804249</presentsUpdate>
					<presentsTotal>36</presentsTotal>
					<presentsAbonnes>24</presentsAbonnes>
					<presentsHoraires>12</presentsHoraires>
				</presents>
			</Parc>
			<Parc>
				<numParc>7</numParc>
				<libelleParc>BOSIO</libelleParc>
				<statusParc>LIBRE</statusParc>
				<placesLibresParc>32</placesLibresParc>
				<placesLibresUpdate>2019-01-05 12:23:45.891624</placesLibresUpdate>
				<presents>
					<presentsUpdate>2019-01-05 12:23:46.659663</presentsUpdate>
					<presentsTotal>254</presentsTotal>
					<presentsAbonnes>238</presentsAbonnes>
					<presentsHoraires>16</presentsHoraires>
				</presents>
			</Parc>
			<Parc>
				<numParc>8</numParc>
				<libelleParc>PLATI</libelleParc>
				<statusParc>LIBRE</statusParc>
				<placesLibresParc>12</placesLibresParc>
				<placesLibresUpdate>2019-01-05 12:23:45.89984</placesLibresUpdate>
				<presents>
					<presentsUpdate>2019-01-05 12:23:46.668046</presentsUpdate>
					<presentsTotal>28</presentsTotal>
					<presentsAbonnes>27</presentsAbonnes>
					<presentsHoraires>1</presentsHoraires>
				</presents>
			</Parc>
		</Quartier>
		<Quartier>
			<nomQuartier>La Rousse</nomQuartier>
			<totalLibresQuartier>82</totalLibresQuartier>
			<totalPresentsQuartier>45</totalPresentsQuartier>
			<totalPresentsHorairesQuartier>6</totalPresentsHorairesQuartier>
			<totalPresentsAbonnesQuartier>39</totalPresentsAbonnesQuartier>
			<Parc>
				<numParc>5</numParc>
				<libelleParc>ANNONCIADE</libelleParc>
				<statusParc>LIBRE</statusParc>
				<placesLibresParc>82</placesLibresParc>
				<placesLibresUpdate>2019-01-05 12:23:45.874281</placesLibresUpdate>
				<presents>
					<presentsUpdate>2019-01-05 12:23:46.642733</presentsUpdate>
					<presentsTotal>45</presentsTotal>
					<presentsAbonnes>39</presentsAbonnes>
					<presentsHoraires>6</presentsHoraires>
				</presents>
			</Parc>
		</Quartier>
		<Quartier>
			<nomQuartier>Larvotto</nomQuartier>
			<totalLibresQuartier>541</totalLibresQuartier>
			<totalPresentsQuartier>472</totalPresentsQuartier>
			<totalPresentsHorairesQuartier>163</totalPresentsHorairesQuartier>
			<totalPresentsAbonnesQuartier>309</totalPresentsAbonnesQuartier>
			<Parc>
				<numParc>3</numParc>
				<libelleParc>LARVOTTO</libelleParc>
				<statusParc>LIBRE</statusParc>
				<placesLibresParc>195</placesLibresParc>
				<placesLibresUpdate>2019-01-05 12:23:45.857323</placesLibresUpdate>
				<presents>
					<presentsUpdate>2019-01-05 12:23:46.626241</presentsUpdate>
					<presentsTotal>170</presentsTotal>
					<presentsAbonnes>109</presentsAbonnes>
					<presentsHoraires>61</presentsHoraires>
				</presents>
			</Parc>
			<Parc>
				<numParc>38</numParc>
				<libelleParc>LES CARMES</libelleParc>
				<statusParc>COMPLET</statusParc>
				<placesLibresParc>0</placesLibresParc>
				<placesLibresUpdate>2019-01-05 12:23:46.093599</placesLibresUpdate>
				<presents>
					<presentsUpdate>2019-01-05 12:23:46.744711</presentsUpdate>
					<presentsTotal>0</presentsTotal>
					<presentsAbonnes>34</presentsAbonnes>
					<presentsHoraires>11</presentsHoraires>
				</presents>
			</Parc>
			<Parc>
				<numParc>4</numParc>
				<libelleParc>GRIMALDI FORUM</libelleParc>
				<statusParc>LIBRE</statusParc>
				<placesLibresParc>313</placesLibresParc>
				<placesLibresUpdate>2019-01-05 12:23:45.866025</placesLibresUpdate>
				<presents>
					<presentsUpdate>2019-01-05 12:23:46.634416</presentsUpdate>
					<presentsTotal>255</presentsTotal>
					<presentsAbonnes>169</presentsAbonnes>
					<presentsHoraires>86</presentsHoraires>
				</presents>
			</Parc>
			<Parc>
				<numParc>43</numParc>
				<libelleParc>TESTIMONIO</libelleParc>
				<statusParc>LIBRE</statusParc>
				<placesLibresParc>33</placesLibresParc>
				<placesLibresUpdate>2019-01-05 12:23:46.12768</placesLibresUpdate>
				<presents>
					<presentsUpdate>2019-01-05 12:23:46.770246</presentsUpdate>
					<presentsTotal>47</presentsTotal>
					<presentsAbonnes>31</presentsAbonnes>
					<presentsHoraires>16</presentsHoraires>
				</presents>
			</Parc>
		</Quartier>
		<Quartier>
			<nomQuartier>Le Rocher</nomQuartier>
			<totalLibresQuartier>271</totalLibresQuartier>
			<totalPresentsQuartier>478</totalPresentsQuartier>
			<totalPresentsHorairesQuartier>201</totalPresentsHorairesQuartier>
			<totalPresentsAbonnesQuartier>277</totalPresentsAbonnesQuartier>
			<Parc>
				<numParc>12</numParc>
				<libelleParc>PECHEURS</libelleParc>
				<statusParc>LIBRE</statusParc>
				<placesLibresParc>198</placesLibresParc>
				<placesLibresUpdate>2019-01-05 12:23:45.916825</placesLibresUpdate>
				<presents>
					<presentsUpdate>2019-01-05 12:23:46.96831</presentsUpdate>
					<presentsTotal>244</presentsTotal>
					<presentsAbonnes>94</presentsAbonnes>
					<presentsHoraires>150</presentsHoraires>
				</presents>
			</Parc>
			<Parc>
				<numParc>17</numParc>
				<libelleParc>ABBAYE</libelleParc>
				<statusParc>LIBRE</statusParc>
				<placesLibresParc>5</placesLibresParc>
				<placesLibresUpdate>2019-01-05 12:23:45.958957</placesLibresUpdate>
				<presents>
					<presentsUpdate>2019-01-05 12:23:46.995646</presentsUpdate>
					<presentsTotal>9</presentsTotal>
					<presentsAbonnes>4</presentsAbonnes>
					<presentsHoraires>5</presentsHoraires>
				</presents>
			</Parc>
			<Parc>
				<numParc>2</numParc>
				<libelleParc>VISITATION</libelleParc>
				<statusParc>LIBRE</statusParc>
				<placesLibresParc>17</placesLibresParc>
				<placesLibresUpdate>2019-01-05 12:23:45.848882</placesLibresUpdate>
				<presents>
					<presentsUpdate>2019-01-05 12:23:46.89714</presentsUpdate>
					<presentsTotal>12</presentsTotal>
					<presentsAbonnes>9</presentsAbonnes>
					<presentsHoraires>3</presentsHoraires>
				</presents>
			</Parc>
			<Parc>
				<numParc>41</numParc>
				<libelleParc>LA DIGUE</libelleParc>
				<statusParc>LIBRE</statusParc>
				<placesLibresParc>51</placesLibresParc>
				<placesLibresUpdate>2019-01-05 12:23:46.110624</placesLibresUpdate>
				<presents>
					<presentsUpdate>2019-01-05 12:23:47.097428</presentsUpdate>
					<presentsTotal>213</presentsTotal>
					<presentsAbonnes>170</presentsAbonnes>
					<presentsHoraires>43</presentsHoraires>
				</presents>
			</Parc>
		</Quartier>
		<Quartier>
			<nomQuartier>Monte-Carlo</nomQuartier>
			<totalLibresQuartier>667</totalLibresQuartier>
			<totalPresentsQuartier>1331</totalPresentsQuartier>
			<totalPresentsHorairesQuartier>515</totalPresentsHorairesQuartier>
			<totalPresentsAbonnesQuartier>816</totalPresentsAbonnesQuartier>
			<Parc>
				<numParc>1</numParc>
				<libelleParc>MOULINS</libelleParc>
				<statusParc>LIBRE</statusParc>
				<placesLibresParc>93</placesLibresParc>
				<placesLibresUpdate>2019-01-05 12:23:45.840441</placesLibresUpdate>
				<presents>
					<presentsUpdate>2019-01-05 12:23:46.617717</presentsUpdate>
					<presentsTotal>185</presentsTotal>
					<presentsAbonnes>111</presentsAbonnes>
					<presentsHoraires>74</presentsHoraires>
				</presents>
			</Parc>
			<Parc>
				<numParc>15</numParc>
				<libelleParc>COSTA</libelleParc>
				<statusParc>LIBRE</statusParc>
				<placesLibresParc>37</placesLibresParc>
				<placesLibresUpdate>2019-01-05 12:23:45.942133</placesLibresUpdate>
				<presents>
					<presentsUpdate>2019-01-05 12:23:46.676439</presentsUpdate>
					<presentsTotal>123</presentsTotal>
					<presentsAbonnes>103</presentsAbonnes>
					<presentsHoraires>20</presentsHoraires>
				</presents>
			</Parc>
			<Parc>
				<numParc>22</numParc>
				<libelleParc>CASINO</libelleParc>
				<statusParc>LIBRE</statusParc>
				<placesLibresParc>181</placesLibresParc>
				<placesLibresUpdate>2019-01-05 12:23:45.983991</placesLibresUpdate>
				<presents>
					<presentsUpdate>2019-01-05 12:23:46.693402</presentsUpdate>
					<presentsTotal>441</presentsTotal>
					<presentsAbonnes>217</presentsAbonnes>
					<presentsHoraires>224</presentsHoraires>
				</presents>
			</Parc>
			<Parc>
				<numParc>26</numParc>
				<libelleParc>ST CHARLES</libelleParc>
				<statusParc>LIBRE</statusParc>
				<placesLibresParc>105</placesLibresParc>
				<placesLibresUpdate>2019-01-05 12:23:46.009212</placesLibresUpdate>
				<presents>
					<presentsUpdate>2019-01-05 12:23:46.702274</presentsUpdate>
					<presentsTotal>210</presentsTotal>
					<presentsAbonnes>140</presentsAbonnes>
					<presentsHoraires>70</presentsHoraires>
				</presents>
			</Parc>
			<Parc>
				<numParc>33</numParc>
				<libelleParc>ST LAURENT</libelleParc>
				<statusParc>LIBRE</statusParc>
				<placesLibresParc>36</placesLibresParc>
				<placesLibresUpdate>2019-01-05 12:23:46.067952</placesLibresUpdate>
				<presents>
					<presentsUpdate>2019-01-05 12:23:46.719314</presentsUpdate>
					<presentsTotal>112</presentsTotal>
					<presentsAbonnes>77</presentsAbonnes>
					<presentsHoraires>35</presentsHoraires>
				</presents>
			</Parc>
			<Parc>
				<numParc>42</numParc>
				<libelleParc>OSTENDE</libelleParc>
				<statusParc>LIBRE</statusParc>
				<placesLibresParc>96</placesLibresParc>
				<placesLibresUpdate>2019-01-05 12:23:46.119165</placesLibresUpdate>
				<presents>
					<presentsUpdate>2019-01-05 12:23:46.761841</presentsUpdate>
					<presentsTotal>61</presentsTotal>
					<presentsAbonnes>32</presentsAbonnes>
					<presentsHoraires>29</presentsHoraires>
				</presents>
			</Parc>
			<Parc>
				<numParc>44</numParc>
				<libelleParc>ROQUEVILLE</libelleParc>
				<statusParc>LIBRE</statusParc>
				<placesLibresParc>65</placesLibresParc>
				<placesLibresUpdate>2019-01-05 12:23:46.136372</placesLibresUpdate>
				<presents>
					<presentsUpdate>2019-01-05 12:23:46.778801</presentsUpdate>
					<presentsTotal>170</presentsTotal>
					<presentsAbonnes>129</presentsAbonnes>
					<presentsHoraires>41</presentsHoraires>
				</presents>
			</Parc>
			<Parc>
				<numParc>6</numParc>
				<libelleParc>LOUIS II</libelleParc>
				<statusParc>LIBRE</statusParc>
				<placesLibresParc>54</placesLibresParc>
				<placesLibresUpdate>2019-01-05 12:23:45.882998</placesLibresUpdate>
				<presents>
					<presentsUpdate>2019-01-05 12:23:46.651338</presentsUpdate>
					<presentsTotal>29</presentsTotal>
					<presentsAbonnes>7</presentsAbonnes>
					<presentsHoraires>22</presentsHoraires>
				</presents>
			</Parc>
		</Quartier>
		<Quartier>
			<nomQuartier>la Condamine</nomQuartier>
			<totalLibresQuartier>479</totalLibresQuartier>
			<totalPresentsQuartier>1008</totalPresentsQuartier>
			<totalPresentsHorairesQuartier>400</totalPresentsHorairesQuartier>
			<totalPresentsAbonnesQuartier>608</totalPresentsAbonnesQuartier>
			<Parc>
				<numParc>28</numParc>
				<libelleParc>CONDAMINE</libelleParc>
				<statusParc>LIBRE</statusParc>
				<placesLibresParc>134</placesLibresParc>
				<placesLibresUpdate>2019-01-05 12:23:46.02596</placesLibresUpdate>
				<presents>
					<presentsUpdate>2019-01-05 12:23:47.0406</presentsUpdate>
					<presentsTotal>232</presentsTotal>
					<presentsAbonnes>167</presentsAbonnes>
					<presentsHoraires>65</presentsHoraires>
				</presents>
			</Parc>
			<Parc>
				<numParc>31</numParc>
				<libelleParc>PLACE D ARMES</libelleParc>
				<statusParc>LIBRE</statusParc>
				<placesLibresParc>3</placesLibresParc>
				<placesLibresUpdate>2019-01-05 12:23:46.051141</placesLibresUpdate>
				<presents>
					<presentsUpdate>2019-01-05 12:23:47.067443</presentsUpdate>
					<presentsTotal>54</presentsTotal>
					<presentsAbonnes>1</presentsAbonnes>
					<presentsHoraires>53</presentsHoraires>
				</presents>
			</Parc>
			<Parc>
				<numParc>32</numParc>
				<libelleParc>QUAI ANTOINE 1ER</libelleParc>
				<statusParc>LIBRE</statusParc>
				<placesLibresParc>149</placesLibresParc>
				<placesLibresUpdate>2019-01-05 12:23:46.059535</placesLibresUpdate>
				<presents>
					<presentsUpdate>2019-01-05 12:23:47.076638</presentsUpdate>
					<presentsTotal>105</presentsTotal>
					<presentsAbonnes>36</presentsAbonnes>
					<presentsHoraires>69</presentsHoraires>
				</presents>
			</Parc>
			<Parc>
				<numParc>36</numParc>
				<libelleParc>SQUARE GASTAUD</libelleParc>
				<statusParc>LIBRE</statusParc>
				<placesLibresParc>47</placesLibresParc>
				<placesLibresUpdate>2019-01-05 12:23:46.085209</placesLibresUpdate>
				<presents>
					<presentsUpdate>2019-01-05 12:23:47.088802</presentsUpdate>
					<presentsTotal>185</presentsTotal>
					<presentsAbonnes>94</presentsAbonnes>
					<presentsHoraires>91</presentsHoraires>
				</presents>
			</Parc>
			<Parc>
				<numParc>39</numParc>
				<libelleParc>LES AGAVES</libelleParc>
				<statusParc>LIBRE</statusParc>
				<placesLibresParc>21</placesLibresParc>
				<placesLibresUpdate>2019-01-05 12:23:46.102125</placesLibresUpdate>
				<presents>
					<presentsUpdate>2019-01-05 12:23:46.753227</presentsUpdate>
					<presentsTotal>68</presentsTotal>
					<presentsAbonnes>58</presentsAbonnes>
					<presentsHoraires>10</presentsHoraires>
				</presents>
			</Parc>
			<Parc>
				<numParc>9</numParc>
				<libelleParc>LA COLLE</libelleParc>
				<statusParc>LIBRE</statusParc>
				<placesLibresParc>125</placesLibresParc>
				<placesLibresUpdate>2019-01-05 12:23:45.908691</placesLibresUpdate>
				<presents>
					<presentsUpdate>2019-01-05 12:23:46.905315</presentsUpdate>
					<presentsTotal>364</presentsTotal>
					<presentsAbonnes>252</presentsAbonnes>
					<presentsHoraires>112</presentsHoraires>
				</presents>
			</Parc>
		</Quartier>
	</Document>
