<?xml version="1.0" encoding="ISO-8859-1"?>
	<Document>
		<totalPresent>4523</totalPresent>
		<totalLibre>4231</totalLibre>
		<lastUpdate>ven., 04 janv. 2019 23:34:01 +0100</lastUpdate>
		<Quartier>
			<nomQuartier>Fontvieille</nomQuartier>
			<totalLibresQuartier>1263</totalLibresQuartier>
			<totalPresentsQuartier>490</totalPresentsQuartier>
			<totalPresentsHorairesQuartier>73</totalPresentsHorairesQuartier>
			<totalPresentsAbonnesQuartier>417</totalPresentsAbonnesQuartier>
			<Parc>
				<numParc>124</numParc>
				<libelleParc>ECOLES RDC</libelleParc>
				<statusParc>LIBRE</statusParc>
				<placesLibresParc>54</placesLibresParc>
				<placesLibresUpdate>2019-01-04 23:33:54.476831</placesLibresUpdate>
				<presents>
					<presentsUpdate>2019-01-04 23:33:54.021803</presentsUpdate>
					<presentsTotal>13</presentsTotal>
					<presentsAbonnes>7</presentsAbonnes>
					<presentsHoraires>6</presentsHoraires>
				</presents>
			</Parc>
			<Parc>
				<numParc>13</numParc>
				<libelleParc>PAPALINS</libelleParc>
				<statusParc>LIBRE</statusParc>
				<placesLibresParc>225</placesLibresParc>
				<placesLibresUpdate>2019-01-04 23:33:54.204815</placesLibresUpdate>
				<presents>
					<presentsUpdate>2019-01-04 23:33:48.665333</presentsUpdate>
					<presentsTotal>33</presentsTotal>
					<presentsAbonnes>28</presentsAbonnes>
					<presentsHoraires>5</presentsHoraires>
				</presents>
			</Parc>
			<Parc>
				<numParc>14</numParc>
				<libelleParc>STADE</libelleParc>
				<statusParc>LIBRE</statusParc>
				<placesLibresParc>238</placesLibresParc>
				<placesLibresUpdate>2019-01-04 23:33:54.213576</placesLibresUpdate>
				<presents>
					<presentsUpdate>2019-01-04 23:33:53.775004</presentsUpdate>
					<presentsTotal>78</presentsTotal>
					<presentsAbonnes>72</presentsAbonnes>
					<presentsHoraires>6</presentsHoraires>
				</presents>
			</Parc>
			<Parc>
				<numParc>21</numParc>
				<libelleParc>PORT</libelleParc>
				<statusParc>LIBRE</statusParc>
				<placesLibresParc>38</placesLibresParc>
				<placesLibresUpdate>2019-01-04 23:33:54.256792</placesLibresUpdate>
				<presents>
					<presentsUpdate>2019-01-04 23:33:53.800737</presentsUpdate>
					<presentsTotal>101</presentsTotal>
					<presentsAbonnes>77</presentsAbonnes>
					<presentsHoraires>24</presentsHoraires>
				</presents>
			</Parc>
			<Parc>
				<numParc>24</numParc>
				<libelleParc>ECOLES</libelleParc>
				<statusParc>LIBRE</statusParc>
				<placesLibresParc>13</placesLibresParc>
				<placesLibresUpdate>2019-01-04 23:33:54.273917</placesLibresUpdate>
				<presents>
					<presentsUpdate>2019-01-04 23:33:53.809505</presentsUpdate>
					<presentsTotal>50</presentsTotal>
					<presentsAbonnes>50</presentsAbonnes>
					<presentsHoraires>0</presentsHoraires>
				</presents>
			</Parc>
			<Parc>
				<numParc>25</numParc>
				<libelleParc>ST NICOLAS</libelleParc>
				<statusParc>LIBRE</statusParc>
				<placesLibresParc>22</placesLibresParc>
				<placesLibresUpdate>2019-01-04 23:33:54.282581</placesLibresUpdate>
				<presents>
					<presentsUpdate>2019-01-04 23:33:53.818003</presentsUpdate>
					<presentsTotal>11</presentsTotal>
					<presentsAbonnes>6</presentsAbonnes>
					<presentsHoraires>5</presentsHoraires>
				</presents>
			</Parc>
			<Parc>
				<numParc>29</numParc>
				<libelleParc>HELIPORT</libelleParc>
				<statusParc>LIBRE</statusParc>
				<placesLibresParc>29</placesLibresParc>
				<placesLibresUpdate>2019-01-04 23:33:54.316689</placesLibresUpdate>
				<presents>
					<presentsUpdate>2019-01-04 23:33:53.835285</presentsUpdate>
					<presentsTotal>24</presentsTotal>
					<presentsAbonnes>22</presentsAbonnes>
					<presentsHoraires>2</presentsHoraires>
				</presents>
			</Parc>
			<Parc>
				<numParc>30</numParc>
				<libelleParc>C.C.F.</libelleParc>
				<statusParc>LIBRE</statusParc>
				<placesLibresParc>551</placesLibresParc>
				<placesLibresUpdate>2019-01-04 23:33:54.324944</placesLibresUpdate>
				<presents>
					<presentsUpdate>2019-01-04 23:33:53.843857</presentsUpdate>
					<presentsTotal>19</presentsTotal>
					<presentsAbonnes>7</presentsAbonnes>
					<presentsHoraires>12</presentsHoraires>
				</presents>
			</Parc>
			<Parc>
				<numParc>52</numParc>
				<libelleParc>ST ANTOINE</libelleParc>
				<statusParc>LIBRE</statusParc>
				<placesLibresParc>93</placesLibresParc>
				<placesLibresUpdate>2019-01-04 23:33:54.44278</placesLibresUpdate>
				<presents>
					<presentsUpdate>2019-01-04 23:33:53.886762</presentsUpdate>
					<presentsTotal>161</presentsTotal>
					<presentsAbonnes>148</presentsAbonnes>
					<presentsHoraires>13</presentsHoraires>
				</presents>
			</Parc>
		</Quartier>
		<Quartier>
			<nomQuartier>I-Cars</nomQuartier>
			<totalLibresQuartier>52</totalLibresQuartier>
			<totalPresentsQuartier>8</totalPresentsQuartier>
			<totalPresentsHorairesQuartier>4</totalPresentsHorairesQuartier>
			<totalPresentsAbonnesQuartier>4</totalPresentsAbonnesQuartier>
			<Parc>
				<numParc>104</numParc>
				<libelleParc>GRIMALDI FORUM BUS</libelleParc>
				<statusParc>LIBRE</statusParc>
				<placesLibresParc>28</placesLibresParc>
				<placesLibresUpdate>2019-01-04 23:33:54.460085</placesLibresUpdate>
				<presents>
					<presentsUpdate>2019-01-04 23:33:43.546437</presentsUpdate>
					<presentsTotal>7</presentsTotal>
					<presentsAbonnes>3</presentsAbonnes>
					<presentsHoraires>4</presentsHoraires>
				</presents>
			</Parc>
			<Parc>
				<numParc>112</numParc>
				<libelleParc>PECHEURS BUS</libelleParc>
				<statusParc>LIBRE</statusParc>
				<placesLibresParc>22</placesLibresParc>
				<placesLibresUpdate>2019-01-04 23:33:54.468365</placesLibresUpdate>
				<presents>
					<presentsUpdate>2019-01-04 23:33:53.988113</presentsUpdate>
					<presentsTotal>1</presentsTotal>
					<presentsAbonnes>1</presentsAbonnes>
					<presentsHoraires>0</presentsHoraires>
				</presents>
			</Parc>
			<Parc>
				<numParc>19</numParc>
				<libelleParc>REGULATION BUS</libelleParc>
				<statusParc>LIBRE</statusParc>
				<placesLibresParc>2</placesLibresParc>
				<placesLibresUpdate>2019-01-04 23:33:54.248343</placesLibresUpdate>
				<presents>
					<presentsUpdate>2010-04-16 09:17:37.639024</presentsUpdate>
					<presentsTotal>0</presentsTotal>
					<presentsAbonnes>Obsolete</presentsAbonnes>
					<presentsHoraires>Obsolete</presentsHoraires>
				</presents>
			</Parc>
		</Quartier>
		<Quartier>
			<nomQuartier>Jardin-Exotique</nomQuartier>
			<totalLibresQuartier>661</totalLibresQuartier>
			<totalPresentsQuartier>1195</totalPresentsQuartier>
			<totalPresentsHorairesQuartier>120</totalPresentsHorairesQuartier>
			<totalPresentsAbonnesQuartier>1075</totalPresentsAbonnesQuartier>
			<Parc>
				<numParc>127</numParc>
				<libelleParc>CHPG 2 (BAS)</libelleParc>
				<statusParc>LIBRE</statusParc>
				<placesLibresParc>223</placesLibresParc>
				<placesLibresUpdate>2019-01-04 23:33:54.485441</placesLibresUpdate>
				<presents>
					<presentsUpdate>2019-01-04 23:33:43.571991</presentsUpdate>
					<presentsTotal>46</presentsTotal>
					<presentsAbonnes>0</presentsAbonnes>
					<presentsHoraires>46</presentsHoraires>
				</presents>
			</Parc>
			<Parc>
				<numParc>16</numParc>
				<libelleParc>JARDIN EXOTIQUE</libelleParc>
				<statusParc>LIBRE</statusParc>
				<placesLibresParc>82</placesLibresParc>
				<placesLibresUpdate>2019-01-04 23:33:54.230514</placesLibresUpdate>
				<presents>
					<presentsUpdate>2019-01-04 23:33:43.41358</presentsUpdate>
					<presentsTotal>288</presentsTotal>
					<presentsAbonnes>270</presentsAbonnes>
					<presentsHoraires>18</presentsHoraires>
				</presents>
			</Parc>
			<Parc>
				<numParc>27</numParc>
				<libelleParc>CHPG 1 (HAUT)</libelleParc>
				<statusParc>COMPLET</statusParc>
				<placesLibresParc>0</placesLibresParc>
				<placesLibresUpdate>2019-01-04 23:33:54.299653</placesLibresUpdate>
				<presents>
					<presentsUpdate>2019-01-04 23:33:43.440843</presentsUpdate>
					<presentsTotal>0</presentsTotal>
					<presentsAbonnes>26</presentsAbonnes>
					<presentsHoraires>0</presentsHoraires>
				</presents>
			</Parc>
			<Parc>
				<numParc>34</numParc>
				<libelleParc>GARE</libelleParc>
				<statusParc>LIBRE</statusParc>
				<placesLibresParc>227</placesLibresParc>
				<placesLibresUpdate>2019-01-04 23:33:54.358821</placesLibresUpdate>
				<presents>
					<presentsUpdate>2019-01-04 23:33:43.459506</presentsUpdate>
					<presentsTotal>506</presentsTotal>
					<presentsAbonnes>487</presentsAbonnes>
					<presentsHoraires>19</presentsHoraires>
				</presents>
			</Parc>
			<Parc>
				<numParc>45</numParc>
				<libelleParc>ATHENA</libelleParc>
				<statusParc>COMPLET</statusParc>
				<placesLibresParc>0</placesLibresParc>
				<placesLibresUpdate>2019-01-04 23:33:54.425939</placesLibresUpdate>
				<presents>
					<presentsUpdate>2019-01-04 23:33:43.519986</presentsUpdate>
					<presentsTotal>0</presentsTotal>
					<presentsAbonnes>12</presentsAbonnes>
					<presentsHoraires>0</presentsHoraires>
				</presents>
			</Parc>
			<Parc>
				<numParc>46</numParc>
				<libelleParc>DES OLIVIERS</libelleParc>
				<statusParc>LIBRE</statusParc>
				<placesLibresParc>25</placesLibresParc>
				<placesLibresUpdate>2019-01-04 23:33:54.434251</placesLibresUpdate>
				<presents>
					<presentsUpdate>2019-01-04 23:33:43.529206</presentsUpdate>
					<presentsTotal>2</presentsTotal>
					<presentsAbonnes>0</presentsAbonnes>
					<presentsHoraires>2</presentsHoraires>
				</presents>
			</Parc>
			<Parc>
				<numParc>60</numParc>
				<libelleParc>ENGELIN</libelleParc>
				<statusParc>LIBRE</statusParc>
				<placesLibresParc>88</placesLibresParc>
				<placesLibresUpdate>2019-01-04 23:33:54.451512</placesLibresUpdate>
				<presents>
					<presentsUpdate>2019-01-04 23:33:43.537597</presentsUpdate>
					<presentsTotal>36</presentsTotal>
					<presentsAbonnes>25</presentsAbonnes>
					<presentsHoraires>11</presentsHoraires>
				</presents>
			</Parc>
			<Parc>
				<numParc>7</numParc>
				<libelleParc>BOSIO</libelleParc>
				<statusParc>LIBRE</statusParc>
				<placesLibresParc>4</placesLibresParc>
				<placesLibresUpdate>2019-01-04 23:33:54.170583</placesLibresUpdate>
				<presents>
					<presentsUpdate>2019-01-04 23:33:43.385957</presentsUpdate>
					<presentsTotal>288</presentsTotal>
					<presentsAbonnes>265</presentsAbonnes>
					<presentsHoraires>23</presentsHoraires>
				</presents>
			</Parc>
			<Parc>
				<numParc>8</numParc>
				<libelleParc>PLATI</libelleParc>
				<statusParc>LIBRE</statusParc>
				<placesLibresParc>12</placesLibresParc>
				<placesLibresUpdate>2019-01-04 23:33:54.179152</placesLibresUpdate>
				<presents>
					<presentsUpdate>2019-01-04 23:33:43.39507</presentsUpdate>
					<presentsTotal>29</presentsTotal>
					<presentsAbonnes>28</presentsAbonnes>
					<presentsHoraires>1</presentsHoraires>
				</presents>
			</Parc>
		</Quartier>
		<Quartier>
			<nomQuartier>La Rousse</nomQuartier>
			<totalLibresQuartier>81</totalLibresQuartier>
			<totalPresentsQuartier>55</totalPresentsQuartier>
			<totalPresentsHorairesQuartier>7</totalPresentsHorairesQuartier>
			<totalPresentsAbonnesQuartier>48</totalPresentsAbonnesQuartier>
			<Parc>
				<numParc>5</numParc>
				<libelleParc>ANNONCIADE</libelleParc>
				<statusParc>LIBRE</statusParc>
				<placesLibresParc>81</placesLibresParc>
				<placesLibresUpdate>2019-01-04 23:33:54.153681</placesLibresUpdate>
				<presents>
					<presentsUpdate>2019-01-04 23:33:43.367571</presentsUpdate>
					<presentsTotal>55</presentsTotal>
					<presentsAbonnes>48</presentsAbonnes>
					<presentsHoraires>7</presentsHoraires>
				</presents>
			</Parc>
		</Quartier>
		<Quartier>
			<nomQuartier>Larvotto</nomQuartier>
			<totalLibresQuartier>432</totalLibresQuartier>
			<totalPresentsQuartier>401</totalPresentsQuartier>
			<totalPresentsHorairesQuartier>117</totalPresentsHorairesQuartier>
			<totalPresentsAbonnesQuartier>284</totalPresentsAbonnesQuartier>
			<Parc>
				<numParc>3</numParc>
				<libelleParc>LARVOTTO</libelleParc>
				<statusParc>LIBRE</statusParc>
				<placesLibresParc>181</placesLibresParc>
				<placesLibresUpdate>2019-01-04 23:33:54.136505</placesLibresUpdate>
				<presents>
					<presentsUpdate>2019-01-04 23:33:43.349496</presentsUpdate>
					<presentsTotal>107</presentsTotal>
					<presentsAbonnes>88</presentsAbonnes>
					<presentsHoraires>19</presentsHoraires>
				</presents>
			</Parc>
			<Parc>
				<numParc>38</numParc>
				<libelleParc>LES CARMES</libelleParc>
				<statusParc>COMPLET</statusParc>
				<placesLibresParc>0</placesLibresParc>
				<placesLibresUpdate>2019-01-04 23:33:54.375679</placesLibresUpdate>
				<presents>
					<presentsUpdate>2019-01-04 23:33:43.477079</presentsUpdate>
					<presentsTotal>0</presentsTotal>
					<presentsAbonnes>35</presentsAbonnes>
					<presentsHoraires>9</presentsHoraires>
				</presents>
			</Parc>
			<Parc>
				<numParc>4</numParc>
				<libelleParc>GRIMALDI FORUM</libelleParc>
				<statusParc>LIBRE</statusParc>
				<placesLibresParc>233</placesLibresParc>
				<placesLibresUpdate>2019-01-04 23:33:54.144877</placesLibresUpdate>
				<presents>
					<presentsUpdate>2019-01-04 23:33:43.358515</presentsUpdate>
					<presentsTotal>226</presentsTotal>
					<presentsAbonnes>159</presentsAbonnes>
					<presentsHoraires>67</presentsHoraires>
				</presents>
			</Parc>
			<Parc>
				<numParc>43</numParc>
				<libelleParc>TESTIMONIO</libelleParc>
				<statusParc>LIBRE</statusParc>
				<placesLibresParc>18</placesLibresParc>
				<placesLibresUpdate>2019-01-04 23:33:54.409034</placesLibresUpdate>
				<presents>
					<presentsUpdate>2019-01-04 23:33:43.502776</presentsUpdate>
					<presentsTotal>68</presentsTotal>
					<presentsAbonnes>37</presentsAbonnes>
					<presentsHoraires>31</presentsHoraires>
				</presents>
			</Parc>
		</Quartier>
		<Quartier>
			<nomQuartier>Le Rocher</nomQuartier>
			<totalLibresQuartier>416</totalLibresQuartier>
			<totalPresentsQuartier>340</totalPresentsQuartier>
			<totalPresentsHorairesQuartier>73</totalPresentsHorairesQuartier>
			<totalPresentsAbonnesQuartier>267</totalPresentsAbonnesQuartier>
			<Parc>
				<numParc>12</numParc>
				<libelleParc>PECHEURS</libelleParc>
				<statusParc>LIBRE</statusParc>
				<placesLibresParc>332</placesLibresParc>
				<placesLibresUpdate>2019-01-04 23:33:54.196234</placesLibresUpdate>
				<presents>
					<presentsUpdate>2019-01-04 23:33:53.766281</presentsUpdate>
					<presentsTotal>101</presentsTotal>
					<presentsAbonnes>86</presentsAbonnes>
					<presentsHoraires>15</presentsHoraires>
				</presents>
			</Parc>
			<Parc>
				<numParc>17</numParc>
				<libelleParc>ABBAYE</libelleParc>
				<statusParc>LIBRE</statusParc>
				<placesLibresParc>14</placesLibresParc>
				<placesLibresUpdate>2019-01-04 23:33:54.239678</placesLibresUpdate>
				<presents>
					<presentsUpdate>2019-01-04 23:33:53.783565</presentsUpdate>
					<presentsTotal>19</presentsTotal>
					<presentsAbonnes>5</presentsAbonnes>
					<presentsHoraires>14</presentsHoraires>
				</presents>
			</Parc>
			<Parc>
				<numParc>2</numParc>
				<libelleParc>VISITATION</libelleParc>
				<statusParc>LIBRE</statusParc>
				<placesLibresParc>20</placesLibresParc>
				<placesLibresUpdate>2019-01-04 23:33:54.128168</placesLibresUpdate>
				<presents>
					<presentsUpdate>2019-01-04 23:33:53.728494</presentsUpdate>
					<presentsTotal>8</presentsTotal>
					<presentsAbonnes>8</presentsAbonnes>
					<presentsHoraires>0</presentsHoraires>
				</presents>
			</Parc>
			<Parc>
				<numParc>41</numParc>
				<libelleParc>LA DIGUE</libelleParc>
				<statusParc>LIBRE</statusParc>
				<placesLibresParc>50</placesLibresParc>
				<placesLibresUpdate>2019-01-04 23:33:54.392526</placesLibresUpdate>
				<presents>
					<presentsUpdate>2019-01-04 23:33:53.878231</presentsUpdate>
					<presentsTotal>212</presentsTotal>
					<presentsAbonnes>168</presentsAbonnes>
					<presentsHoraires>44</presentsHoraires>
				</presents>
			</Parc>
		</Quartier>
		<Quartier>
			<nomQuartier>Monte-Carlo</nomQuartier>
			<totalLibresQuartier>785</totalLibresQuartier>
			<totalPresentsQuartier>1160</totalPresentsQuartier>
			<totalPresentsHorairesQuartier>365</totalPresentsHorairesQuartier>
			<totalPresentsAbonnesQuartier>795</totalPresentsAbonnesQuartier>
			<Parc>
				<numParc>1</numParc>
				<libelleParc>MOULINS</libelleParc>
				<statusParc>LIBRE</statusParc>
				<placesLibresParc>120</placesLibresParc>
				<placesLibresUpdate>2019-01-04 23:33:54.115401</placesLibresUpdate>
				<presents>
					<presentsUpdate>2019-01-04 23:33:43.332339</presentsUpdate>
					<presentsTotal>175</presentsTotal>
					<presentsAbonnes>128</presentsAbonnes>
					<presentsHoraires>47</presentsHoraires>
				</presents>
			</Parc>
			<Parc>
				<numParc>15</numParc>
				<libelleParc>COSTA</libelleParc>
				<statusParc>LIBRE</statusParc>
				<placesLibresParc>38</placesLibresParc>
				<placesLibresUpdate>2019-01-04 23:33:54.22201</placesLibresUpdate>
				<presents>
					<presentsUpdate>2019-01-04 23:33:43.404198</presentsUpdate>
					<presentsTotal>129</presentsTotal>
					<presentsAbonnes>112</presentsAbonnes>
					<presentsHoraires>17</presentsHoraires>
				</presents>
			</Parc>
			<Parc>
				<numParc>22</numParc>
				<libelleParc>CASINO</libelleParc>
				<statusParc>LIBRE</statusParc>
				<placesLibresParc>226</placesLibresParc>
				<placesLibresUpdate>2019-01-04 23:33:54.265448</placesLibresUpdate>
				<presents>
					<presentsUpdate>2019-01-04 23:33:43.422514</presentsUpdate>
					<presentsTotal>330</presentsTotal>
					<presentsAbonnes>157</presentsAbonnes>
					<presentsHoraires>173</presentsHoraires>
				</presents>
			</Parc>
			<Parc>
				<numParc>26</numParc>
				<libelleParc>ST CHARLES</libelleParc>
				<statusParc>LIBRE</statusParc>
				<placesLibresParc>154</placesLibresParc>
				<placesLibresUpdate>2019-01-04 23:33:54.291306</placesLibresUpdate>
				<presents>
					<presentsUpdate>2019-01-04 23:33:43.431885</presentsUpdate>
					<presentsTotal>164</presentsTotal>
					<presentsAbonnes>143</presentsAbonnes>
					<presentsHoraires>21</presentsHoraires>
				</presents>
			</Parc>
			<Parc>
				<numParc>33</numParc>
				<libelleParc>ST LAURENT</libelleParc>
				<statusParc>LIBRE</statusParc>
				<placesLibresParc>54</placesLibresParc>
				<placesLibresUpdate>2019-01-04 23:33:54.350476</placesLibresUpdate>
				<presents>
					<presentsUpdate>2019-01-04 23:33:43.450441</presentsUpdate>
					<presentsTotal>104</presentsTotal>
					<presentsAbonnes>86</presentsAbonnes>
					<presentsHoraires>18</presentsHoraires>
				</presents>
			</Parc>
			<Parc>
				<numParc>42</numParc>
				<libelleParc>OSTENDE</libelleParc>
				<statusParc>LIBRE</statusParc>
				<placesLibresParc>75</placesLibresParc>
				<placesLibresUpdate>2019-01-04 23:33:54.400732</placesLibresUpdate>
				<presents>
					<presentsUpdate>2019-01-04 23:33:43.494235</presentsUpdate>
					<presentsTotal>50</presentsTotal>
					<presentsAbonnes>25</presentsAbonnes>
					<presentsHoraires>25</presentsHoraires>
				</presents>
			</Parc>
			<Parc>
				<numParc>44</numParc>
				<libelleParc>ROQUEVILLE</libelleParc>
				<statusParc>LIBRE</statusParc>
				<placesLibresParc>78</placesLibresParc>
				<placesLibresUpdate>2019-01-04 23:33:54.417605</placesLibresUpdate>
				<presents>
					<presentsUpdate>2019-01-04 23:33:43.511353</presentsUpdate>
					<presentsTotal>168</presentsTotal>
					<presentsAbonnes>140</presentsAbonnes>
					<presentsHoraires>28</presentsHoraires>
				</presents>
			</Parc>
			<Parc>
				<numParc>6</numParc>
				<libelleParc>LOUIS II</libelleParc>
				<statusParc>LIBRE</statusParc>
				<placesLibresParc>40</placesLibresParc>
				<placesLibresUpdate>2019-01-04 23:33:54.162154</placesLibresUpdate>
				<presents>
					<presentsUpdate>2019-01-04 23:33:43.37695</presentsUpdate>
					<presentsTotal>40</presentsTotal>
					<presentsAbonnes>4</presentsAbonnes>
					<presentsHoraires>36</presentsHoraires>
				</presents>
			</Parc>
		</Quartier>
		<Quartier>
			<nomQuartier>la Condamine</nomQuartier>
			<totalLibresQuartier>541</totalLibresQuartier>
			<totalPresentsQuartier>874</totalPresentsQuartier>
			<totalPresentsHorairesQuartier>266</totalPresentsHorairesQuartier>
			<totalPresentsAbonnesQuartier>608</totalPresentsAbonnesQuartier>
			<Parc>
				<numParc>28</numParc>
				<libelleParc>CONDAMINE</libelleParc>
				<statusParc>LIBRE</statusParc>
				<placesLibresParc>89</placesLibresParc>
				<placesLibresUpdate>2019-01-04 23:33:54.308287</placesLibresUpdate>
				<presents>
					<presentsUpdate>2019-01-04 23:33:53.826637</presentsUpdate>
					<presentsTotal>196</presentsTotal>
					<presentsAbonnes>163</presentsAbonnes>
					<presentsHoraires>33</presentsHoraires>
				</presents>
			</Parc>
			<Parc>
				<numParc>31</numParc>
				<libelleParc>PLACE D ARMES</libelleParc>
				<statusParc>LIBRE</statusParc>
				<placesLibresParc>39</placesLibresParc>
				<placesLibresUpdate>2019-01-04 23:33:54.33339</placesLibresUpdate>
				<presents>
					<presentsUpdate>2019-01-04 23:33:53.852481</presentsUpdate>
					<presentsTotal>19</presentsTotal>
					<presentsAbonnes>0</presentsAbonnes>
					<presentsHoraires>19</presentsHoraires>
				</presents>
			</Parc>
			<Parc>
				<numParc>32</numParc>
				<libelleParc>QUAI ANTOINE 1ER</libelleParc>
				<statusParc>LIBRE</statusParc>
				<placesLibresParc>78</placesLibresParc>
				<placesLibresUpdate>2019-01-04 23:33:54.342034</placesLibresUpdate>
				<presents>
					<presentsUpdate>2019-01-04 23:33:53.861234</presentsUpdate>
					<presentsTotal>177</presentsTotal>
					<presentsAbonnes>36</presentsAbonnes>
					<presentsHoraires>141</presentsHoraires>
				</presents>
			</Parc>
			<Parc>
				<numParc>36</numParc>
				<libelleParc>SQUARE GASTAUD</libelleParc>
				<statusParc>LIBRE</statusParc>
				<placesLibresParc>94</placesLibresParc>
				<placesLibresUpdate>2019-01-04 23:33:54.367282</placesLibresUpdate>
				<presents>
					<presentsUpdate>2019-01-04 23:33:53.869586</presentsUpdate>
					<presentsTotal>140</presentsTotal>
					<presentsAbonnes>102</presentsAbonnes>
					<presentsHoraires>38</presentsHoraires>
				</presents>
			</Parc>
			<Parc>
				<numParc>39</numParc>
				<libelleParc>LES AGAVES</libelleParc>
				<statusParc>LIBRE</statusParc>
				<placesLibresParc>23</placesLibresParc>
				<placesLibresUpdate>2019-01-04 23:33:54.384085</placesLibresUpdate>
				<presents>
					<presentsUpdate>2019-01-04 23:33:43.485655</presentsUpdate>
					<presentsTotal>70</presentsTotal>
					<presentsAbonnes>63</presentsAbonnes>
					<presentsHoraires>7</presentsHoraires>
				</presents>
			</Parc>
			<Parc>
				<numParc>9</numParc>
				<libelleParc>LA COLLE</libelleParc>
				<statusParc>LIBRE</statusParc>
				<placesLibresParc>218</placesLibresParc>
				<placesLibresUpdate>2019-01-04 23:33:54.187878</placesLibresUpdate>
				<presents>
					<presentsUpdate>2019-01-04 23:33:53.742295</presentsUpdate>
					<presentsTotal>272</presentsTotal>
					<presentsAbonnes>244</presentsAbonnes>
					<presentsHoraires>28</presentsHoraires>
				</presents>
			</Parc>
		</Quartier>
	</Document>
