<?xml version="1.0" encoding="ISO-8859-1"?>
	<Document>
		<totalPresent>4436</totalPresent>
		<totalLibre>4746</totalLibre>
		<lastUpdate>mar., 01 janv. 2019 05:34:01 +0100</lastUpdate>
		<Quartier>
			<nomQuartier>Fontvieille</nomQuartier>
			<totalLibresQuartier>1264</totalLibresQuartier>
			<totalPresentsQuartier>519</totalPresentsQuartier>
			<totalPresentsHorairesQuartier>128</totalPresentsHorairesQuartier>
			<totalPresentsAbonnesQuartier>391</totalPresentsAbonnesQuartier>
			<Parc>
				<numParc>124</numParc>
				<libelleParc>ECOLES RDC</libelleParc>
				<statusParc>LIBRE</statusParc>
				<placesLibresParc>55</placesLibresParc>
				<placesLibresUpdate>2019-01-01 05:33:44.196644</placesLibresUpdate>
				<presents>
					<presentsUpdate>2019-01-01 05:33:44.896989</presentsUpdate>
					<presentsTotal>16</presentsTotal>
					<presentsAbonnes>10</presentsAbonnes>
					<presentsHoraires>6</presentsHoraires>
				</presents>
			</Parc>
			<Parc>
				<numParc>13</numParc>
				<libelleParc>PAPALINS</libelleParc>
				<statusParc>LIBRE</statusParc>
				<placesLibresParc>226</placesLibresParc>
				<placesLibresUpdate>2019-01-01 05:33:43.808167</placesLibresUpdate>
				<presents>
					<presentsUpdate>2019-01-01 05:33:45.057512</presentsUpdate>
					<presentsTotal>31</presentsTotal>
					<presentsAbonnes>26</presentsAbonnes>
					<presentsHoraires>5</presentsHoraires>
				</presents>
			</Parc>
			<Parc>
				<numParc>14</numParc>
				<libelleParc>STADE</libelleParc>
				<statusParc>LIBRE</statusParc>
				<placesLibresParc>231</placesLibresParc>
				<placesLibresUpdate>2019-01-01 05:33:43.81681</placesLibresUpdate>
				<presents>
					<presentsUpdate>2019-01-01 05:33:44.710581</presentsUpdate>
					<presentsTotal>79</presentsTotal>
					<presentsAbonnes>67</presentsAbonnes>
					<presentsHoraires>12</presentsHoraires>
				</presents>
			</Parc>
			<Parc>
				<numParc>21</numParc>
				<libelleParc>PORT</libelleParc>
				<statusParc>LIBRE</statusParc>
				<placesLibresParc>78</placesLibresParc>
				<placesLibresUpdate>2019-01-01 05:33:43.859314</placesLibresUpdate>
				<presents>
					<presentsUpdate>2019-01-01 05:33:44.736089</presentsUpdate>
					<presentsTotal>93</presentsTotal>
					<presentsAbonnes>71</presentsAbonnes>
					<presentsHoraires>22</presentsHoraires>
				</presents>
			</Parc>
			<Parc>
				<numParc>24</numParc>
				<libelleParc>ECOLES</libelleParc>
				<statusParc>LIBRE</statusParc>
				<placesLibresParc>14</placesLibresParc>
				<placesLibresUpdate>2019-01-01 05:33:43.876127</placesLibresUpdate>
				<presents>
					<presentsUpdate>2019-01-01 05:33:44.744207</presentsUpdate>
					<presentsTotal>51</presentsTotal>
					<presentsAbonnes>51</presentsAbonnes>
					<presentsHoraires>0</presentsHoraires>
				</presents>
			</Parc>
			<Parc>
				<numParc>25</numParc>
				<libelleParc>ST NICOLAS</libelleParc>
				<statusParc>LIBRE</statusParc>
				<placesLibresParc>74</placesLibresParc>
				<placesLibresUpdate>2019-01-01 05:33:43.884611</placesLibresUpdate>
				<presents>
					<presentsUpdate>2019-01-01 05:33:44.752648</presentsUpdate>
					<presentsTotal>10</presentsTotal>
					<presentsAbonnes>7</presentsAbonnes>
					<presentsHoraires>3</presentsHoraires>
				</presents>
			</Parc>
			<Parc>
				<numParc>29</numParc>
				<libelleParc>HELIPORT</libelleParc>
				<statusParc>LIBRE</statusParc>
				<placesLibresParc>4</placesLibresParc>
				<placesLibresUpdate>2019-01-01 05:33:43.918185</placesLibresUpdate>
				<presents>
					<presentsUpdate>2019-01-01 05:33:44.769404</presentsUpdate>
					<presentsTotal>59</presentsTotal>
					<presentsAbonnes>23</presentsAbonnes>
					<presentsHoraires>36</presentsHoraires>
				</presents>
			</Parc>
			<Parc>
				<numParc>30</numParc>
				<libelleParc>C.C.F.</libelleParc>
				<statusParc>LIBRE</statusParc>
				<placesLibresParc>533</placesLibresParc>
				<placesLibresUpdate>2019-01-01 05:33:43.926604</placesLibresUpdate>
				<presents>
					<presentsUpdate>2019-01-01 05:33:44.77808</presentsUpdate>
					<presentsTotal>36</presentsTotal>
					<presentsAbonnes>6</presentsAbonnes>
					<presentsHoraires>30</presentsHoraires>
				</presents>
			</Parc>
			<Parc>
				<numParc>52</numParc>
				<libelleParc>ST ANTOINE</libelleParc>
				<statusParc>LIBRE</statusParc>
				<placesLibresParc>49</placesLibresParc>
				<placesLibresUpdate>2019-01-01 05:33:44.16275</placesLibresUpdate>
				<presents>
					<presentsUpdate>2019-01-01 05:33:44.820272</presentsUpdate>
					<presentsTotal>144</presentsTotal>
					<presentsAbonnes>130</presentsAbonnes>
					<presentsHoraires>14</presentsHoraires>
				</presents>
			</Parc>
		</Quartier>
		<Quartier>
			<nomQuartier>I-Cars</nomQuartier>
			<totalLibresQuartier>25</totalLibresQuartier>
			<totalPresentsQuartier>9</totalPresentsQuartier>
			<totalPresentsHorairesQuartier>5</totalPresentsHorairesQuartier>
			<totalPresentsAbonnesQuartier>4</totalPresentsAbonnesQuartier>
			<Parc>
				<numParc>104</numParc>
				<libelleParc>GRIMALDI FORUM BUS</libelleParc>
				<statusParc>LIBRE</statusParc>
				<placesLibresParc>0</placesLibresParc>
				<placesLibresUpdate>2019-01-01 05:33:44.179503</placesLibresUpdate>
				<presents>
					<presentsUpdate>2019-01-01 05:33:44.583981</presentsUpdate>
					<presentsTotal>8</presentsTotal>
					<presentsAbonnes>3</presentsAbonnes>
					<presentsHoraires>5</presentsHoraires>
				</presents>
			</Parc>
			<Parc>
				<numParc>112</numParc>
				<libelleParc>PECHEURS BUS</libelleParc>
				<statusParc>LIBRE</statusParc>
				<placesLibresParc>22</placesLibresParc>
				<placesLibresUpdate>2019-01-01 05:33:44.188011</placesLibresUpdate>
				<presents>
					<presentsUpdate>2019-01-01 05:33:44.862992</presentsUpdate>
					<presentsTotal>1</presentsTotal>
					<presentsAbonnes>1</presentsAbonnes>
					<presentsHoraires>0</presentsHoraires>
				</presents>
			</Parc>
			<Parc>
				<numParc>19</numParc>
				<libelleParc>REGULATION BUS</libelleParc>
				<statusParc>LIBRE</statusParc>
				<placesLibresParc>3</placesLibresParc>
				<placesLibresUpdate>2019-01-01 05:33:43.850763</placesLibresUpdate>
				<presents>
					<presentsUpdate>2010-04-16 09:17:37.639024</presentsUpdate>
					<presentsTotal>0</presentsTotal>
					<presentsAbonnes>Obsolete</presentsAbonnes>
					<presentsHoraires>Obsolete</presentsHoraires>
				</presents>
			</Parc>
		</Quartier>
		<Quartier>
			<nomQuartier>Jardin-Exotique</nomQuartier>
			<totalLibresQuartier>665</totalLibresQuartier>
			<totalPresentsQuartier>1146</totalPresentsQuartier>
			<totalPresentsHorairesQuartier>119</totalPresentsHorairesQuartier>
			<totalPresentsAbonnesQuartier>1027</totalPresentsAbonnesQuartier>
			<Parc>
				<numParc>127</numParc>
				<libelleParc>CHPG 2 (BAS)</libelleParc>
				<statusParc>LIBRE</statusParc>
				<placesLibresParc>242</placesLibresParc>
				<placesLibresUpdate>2019-01-01 05:33:44.205225</placesLibresUpdate>
				<presents>
					<presentsUpdate>2019-01-01 05:33:44.609395</presentsUpdate>
					<presentsTotal>27</presentsTotal>
					<presentsAbonnes>0</presentsAbonnes>
					<presentsHoraires>27</presentsHoraires>
				</presents>
			</Parc>
			<Parc>
				<numParc>16</numParc>
				<libelleParc>JARDIN EXOTIQUE</libelleParc>
				<statusParc>LIBRE</statusParc>
				<placesLibresParc>87</placesLibresParc>
				<placesLibresUpdate>2019-01-01 05:33:43.833824</placesLibresUpdate>
				<presents>
					<presentsUpdate>2019-01-01 05:33:44.389786</presentsUpdate>
					<presentsTotal>273</presentsTotal>
					<presentsAbonnes>261</presentsAbonnes>
					<presentsHoraires>12</presentsHoraires>
				</presents>
			</Parc>
			<Parc>
				<numParc>27</numParc>
				<libelleParc>CHPG 1 (HAUT)</libelleParc>
				<statusParc>COMPLET</statusParc>
				<placesLibresParc>0</placesLibresParc>
				<placesLibresUpdate>2019-01-01 05:33:43.901573</placesLibresUpdate>
				<presents>
					<presentsUpdate>2019-01-01 05:33:44.415195</presentsUpdate>
					<presentsTotal>0</presentsTotal>
					<presentsAbonnes>22</presentsAbonnes>
					<presentsHoraires>0</presentsHoraires>
				</presents>
			</Parc>
			<Parc>
				<numParc>34</numParc>
				<libelleParc>GARE</libelleParc>
				<statusParc>LIBRE</statusParc>
				<placesLibresParc>198</placesLibresParc>
				<placesLibresUpdate>2019-01-01 05:33:43.96074</placesLibresUpdate>
				<presents>
					<presentsUpdate>2019-01-01 05:33:44.432106</presentsUpdate>
					<presentsTotal>513</presentsTotal>
					<presentsAbonnes>464</presentsAbonnes>
					<presentsHoraires>49</presentsHoraires>
				</presents>
			</Parc>
			<Parc>
				<numParc>45</numParc>
				<libelleParc>ATHENA</libelleParc>
				<statusParc>COMPLET</statusParc>
				<placesLibresParc>0</placesLibresParc>
				<placesLibresUpdate>2019-01-01 05:33:44.145647</placesLibresUpdate>
				<presents>
					<presentsUpdate>2019-01-01 05:33:44.55818</presentsUpdate>
					<presentsTotal>0</presentsTotal>
					<presentsAbonnes>13</presentsAbonnes>
					<presentsHoraires>0</presentsHoraires>
				</presents>
			</Parc>
			<Parc>
				<numParc>46</numParc>
				<libelleParc>DES OLIVIERS</libelleParc>
				<statusParc>LIBRE</statusParc>
				<placesLibresParc>25</placesLibresParc>
				<placesLibresUpdate>2019-01-01 05:33:44.153961</placesLibresUpdate>
				<presents>
					<presentsUpdate>2019-01-01 05:33:44.566988</presentsUpdate>
					<presentsTotal>2</presentsTotal>
					<presentsAbonnes>0</presentsAbonnes>
					<presentsHoraires>2</presentsHoraires>
				</presents>
			</Parc>
			<Parc>
				<numParc>60</numParc>
				<libelleParc>ENGELIN</libelleParc>
				<statusParc>LIBRE</statusParc>
				<placesLibresParc>91</placesLibresParc>
				<placesLibresUpdate>2019-01-01 05:33:44.171102</placesLibresUpdate>
				<presents>
					<presentsUpdate>2019-01-01 05:33:44.575268</presentsUpdate>
					<presentsTotal>35</presentsTotal>
					<presentsAbonnes>26</presentsAbonnes>
					<presentsHoraires>9</presentsHoraires>
				</presents>
			</Parc>
			<Parc>
				<numParc>7</numParc>
				<libelleParc>BOSIO</libelleParc>
				<statusParc>LIBRE</statusParc>
				<placesLibresParc>12</placesLibresParc>
				<placesLibresUpdate>2019-01-01 05:33:43.770272</placesLibresUpdate>
				<presents>
					<presentsUpdate>2019-01-01 05:33:44.297963</presentsUpdate>
					<presentsTotal>264</presentsTotal>
					<presentsAbonnes>247</presentsAbonnes>
					<presentsHoraires>17</presentsHoraires>
				</presents>
			</Parc>
			<Parc>
				<numParc>8</numParc>
				<libelleParc>PLATI</libelleParc>
				<statusParc>LIBRE</statusParc>
				<placesLibresParc>10</placesLibresParc>
				<placesLibresUpdate>2019-01-01 05:33:43.779745</placesLibresUpdate>
				<presents>
					<presentsUpdate>2019-01-01 05:33:44.306391</presentsUpdate>
					<presentsTotal>32</presentsTotal>
					<presentsAbonnes>29</presentsAbonnes>
					<presentsHoraires>3</presentsHoraires>
				</presents>
			</Parc>
		</Quartier>
		<Quartier>
			<nomQuartier>La Rousse</nomQuartier>
			<totalLibresQuartier>81</totalLibresQuartier>
			<totalPresentsQuartier>49</totalPresentsQuartier>
			<totalPresentsHorairesQuartier>7</totalPresentsHorairesQuartier>
			<totalPresentsAbonnesQuartier>42</totalPresentsAbonnesQuartier>
			<Parc>
				<numParc>5</numParc>
				<libelleParc>ANNONCIADE</libelleParc>
				<statusParc>LIBRE</statusParc>
				<placesLibresParc>81</placesLibresParc>
				<placesLibresUpdate>2019-01-01 05:33:43.751694</placesLibresUpdate>
				<presents>
					<presentsUpdate>2019-01-01 05:33:44.281049</presentsUpdate>
					<presentsTotal>49</presentsTotal>
					<presentsAbonnes>42</presentsAbonnes>
					<presentsHoraires>7</presentsHoraires>
				</presents>
			</Parc>
		</Quartier>
		<Quartier>
			<nomQuartier>Larvotto</nomQuartier>
			<totalLibresQuartier>601</totalLibresQuartier>
			<totalPresentsQuartier>523</totalPresentsQuartier>
			<totalPresentsHorairesQuartier>245</totalPresentsHorairesQuartier>
			<totalPresentsAbonnesQuartier>278</totalPresentsAbonnesQuartier>
			<Parc>
				<numParc>3</numParc>
				<libelleParc>LARVOTTO</libelleParc>
				<statusParc>LIBRE</statusParc>
				<placesLibresParc>236</placesLibresParc>
				<placesLibresUpdate>2019-01-01 05:33:43.733345</placesLibresUpdate>
				<presents>
					<presentsUpdate>2019-01-01 05:33:44.264421</presentsUpdate>
					<presentsTotal>128</presentsTotal>
					<presentsAbonnes>74</presentsAbonnes>
					<presentsHoraires>54</presentsHoraires>
				</presents>
			</Parc>
			<Parc>
				<numParc>38</numParc>
				<libelleParc>LES CARMES</libelleParc>
				<statusParc>LIBRE</statusParc>
				<placesLibresParc>6</placesLibresParc>
				<placesLibresUpdate>2019-01-01 05:33:43.977755</placesLibresUpdate>
				<presents>
					<presentsUpdate>2019-01-01 05:33:44.448877</presentsUpdate>
					<presentsTotal>45</presentsTotal>
					<presentsAbonnes>35</presentsAbonnes>
					<presentsHoraires>10</presentsHoraires>
				</presents>
			</Parc>
			<Parc>
				<numParc>4</numParc>
				<libelleParc>GRIMALDI FORUM</libelleParc>
				<statusParc>LIBRE</statusParc>
				<placesLibresParc>346</placesLibresParc>
				<placesLibresUpdate>2019-01-01 05:33:43.742437</placesLibresUpdate>
				<presents>
					<presentsUpdate>2019-01-01 05:33:44.272676</presentsUpdate>
					<presentsTotal>279</presentsTotal>
					<presentsAbonnes>135</presentsAbonnes>
					<presentsHoraires>144</presentsHoraires>
				</presents>
			</Parc>
			<Parc>
				<numParc>43</numParc>
				<libelleParc>TESTIMONIO</libelleParc>
				<statusParc>LIBRE</statusParc>
				<placesLibresParc>13</placesLibresParc>
				<placesLibresUpdate>2019-01-01 05:33:44.065258</placesLibresUpdate>
				<presents>
					<presentsUpdate>2019-01-01 05:33:44.541439</presentsUpdate>
					<presentsTotal>71</presentsTotal>
					<presentsAbonnes>34</presentsAbonnes>
					<presentsHoraires>37</presentsHoraires>
				</presents>
			</Parc>
		</Quartier>
		<Quartier>
			<nomQuartier>Le Rocher</nomQuartier>
			<totalLibresQuartier>446</totalLibresQuartier>
			<totalPresentsQuartier>347</totalPresentsQuartier>
			<totalPresentsHorairesQuartier>77</totalPresentsHorairesQuartier>
			<totalPresentsAbonnesQuartier>270</totalPresentsAbonnesQuartier>
			<Parc>
				<numParc>12</numParc>
				<libelleParc>PECHEURS</libelleParc>
				<statusParc>LIBRE</statusParc>
				<placesLibresParc>361</placesLibresParc>
				<placesLibresUpdate>2019-01-01 05:33:43.797874</placesLibresUpdate>
				<presents>
					<presentsUpdate>2019-01-01 05:33:44.702226</presentsUpdate>
					<presentsTotal>132</presentsTotal>
					<presentsAbonnes>96</presentsAbonnes>
					<presentsHoraires>36</presentsHoraires>
				</presents>
			</Parc>
			<Parc>
				<numParc>17</numParc>
				<libelleParc>ABBAYE</libelleParc>
				<statusParc>LIBRE</statusParc>
				<placesLibresParc>6</placesLibresParc>
				<placesLibresUpdate>2019-01-01 05:33:43.842329</placesLibresUpdate>
				<presents>
					<presentsUpdate>2019-01-01 05:33:44.71924</presentsUpdate>
					<presentsTotal>11</presentsTotal>
					<presentsAbonnes>5</presentsAbonnes>
					<presentsHoraires>6</presentsHoraires>
				</presents>
			</Parc>
			<Parc>
				<numParc>2</numParc>
				<libelleParc>VISITATION</libelleParc>
				<statusParc>LIBRE</statusParc>
				<placesLibresParc>20</placesLibresParc>
				<placesLibresUpdate>2019-01-01 05:33:43.724053</placesLibresUpdate>
				<presents>
					<presentsUpdate>2019-01-01 05:33:44.66893</presentsUpdate>
					<presentsTotal>8</presentsTotal>
					<presentsAbonnes>8</presentsAbonnes>
					<presentsHoraires>0</presentsHoraires>
				</presents>
			</Parc>
			<Parc>
				<numParc>41</numParc>
				<libelleParc>LA DIGUE</libelleParc>
				<statusParc>LIBRE</statusParc>
				<placesLibresParc>59</placesLibresParc>
				<placesLibresUpdate>2019-01-01 05:33:43.99483</placesLibresUpdate>
				<presents>
					<presentsUpdate>2019-01-01 05:33:44.811728</presentsUpdate>
					<presentsTotal>196</presentsTotal>
					<presentsAbonnes>161</presentsAbonnes>
					<presentsHoraires>35</presentsHoraires>
				</presents>
			</Parc>
		</Quartier>
		<Quartier>
			<nomQuartier>Monte-Carlo</nomQuartier>
			<totalLibresQuartier>905</totalLibresQuartier>
			<totalPresentsQuartier>1107</totalPresentsQuartier>
			<totalPresentsHorairesQuartier>369</totalPresentsHorairesQuartier>
			<totalPresentsAbonnesQuartier>738</totalPresentsAbonnesQuartier>
			<Parc>
				<numParc>1</numParc>
				<libelleParc>MOULINS</libelleParc>
				<statusParc>LIBRE</statusParc>
				<placesLibresParc>97</placesLibresParc>
				<placesLibresUpdate>2019-01-01 05:33:43.71713</placesLibresUpdate>
				<presents>
					<presentsUpdate>2019-01-01 05:33:44.25603</presentsUpdate>
					<presentsTotal>195</presentsTotal>
					<presentsAbonnes>125</presentsAbonnes>
					<presentsHoraires>70</presentsHoraires>
				</presents>
			</Parc>
			<Parc>
				<numParc>15</numParc>
				<libelleParc>COSTA</libelleParc>
				<statusParc>LIBRE</statusParc>
				<placesLibresParc>59</placesLibresParc>
				<placesLibresUpdate>2019-01-01 05:33:43.825221</placesLibresUpdate>
				<presents>
					<presentsUpdate>2019-01-01 05:33:44.381356</presentsUpdate>
					<presentsTotal>129</presentsTotal>
					<presentsAbonnes>100</presentsAbonnes>
					<presentsHoraires>29</presentsHoraires>
				</presents>
			</Parc>
			<Parc>
				<numParc>22</numParc>
				<libelleParc>CASINO</libelleParc>
				<statusParc>LIBRE</statusParc>
				<placesLibresParc>308</placesLibresParc>
				<placesLibresUpdate>2019-01-01 05:33:43.867778</placesLibresUpdate>
				<presents>
					<presentsUpdate>2019-01-01 05:33:44.398424</presentsUpdate>
					<presentsTotal>204</presentsTotal>
					<presentsAbonnes>103</presentsAbonnes>
					<presentsHoraires>101</presentsHoraires>
				</presents>
			</Parc>
			<Parc>
				<numParc>26</numParc>
				<libelleParc>ST CHARLES</libelleParc>
				<statusParc>LIBRE</statusParc>
				<placesLibresParc>208</placesLibresParc>
				<placesLibresUpdate>2019-01-01 05:33:43.893001</placesLibresUpdate>
				<presents>
					<presentsUpdate>2019-01-01 05:33:44.406614</presentsUpdate>
					<presentsTotal>165</presentsTotal>
					<presentsAbonnes>138</presentsAbonnes>
					<presentsHoraires>27</presentsHoraires>
				</presents>
			</Parc>
			<Parc>
				<numParc>33</numParc>
				<libelleParc>ST LAURENT</libelleParc>
				<statusParc>LIBRE</statusParc>
				<placesLibresParc>49</placesLibresParc>
				<placesLibresUpdate>2019-01-01 05:33:43.951902</placesLibresUpdate>
				<presents>
					<presentsUpdate>2019-01-01 05:33:44.423528</presentsUpdate>
					<presentsTotal>112</presentsTotal>
					<presentsAbonnes>90</presentsAbonnes>
					<presentsHoraires>22</presentsHoraires>
				</presents>
			</Parc>
			<Parc>
				<numParc>42</numParc>
				<libelleParc>OSTENDE</libelleParc>
				<statusParc>LIBRE</statusParc>
				<placesLibresParc>117</placesLibresParc>
				<placesLibresUpdate>2019-01-01 05:33:44.003158</placesLibresUpdate>
				<presents>
					<presentsUpdate>2019-01-01 05:33:44.532625</presentsUpdate>
					<presentsTotal>47</presentsTotal>
					<presentsAbonnes>30</presentsAbonnes>
					<presentsHoraires>17</presentsHoraires>
				</presents>
			</Parc>
			<Parc>
				<numParc>44</numParc>
				<libelleParc>ROQUEVILLE</libelleParc>
				<statusParc>LIBRE</statusParc>
				<placesLibresParc>46</placesLibresParc>
				<placesLibresUpdate>2019-01-01 05:33:44.136842</placesLibresUpdate>
				<presents>
					<presentsUpdate>2019-01-01 05:33:44.549862</presentsUpdate>
					<presentsTotal>172</presentsTotal>
					<presentsAbonnes>132</presentsAbonnes>
					<presentsHoraires>40</presentsHoraires>
				</presents>
			</Parc>
			<Parc>
				<numParc>6</numParc>
				<libelleParc>LOUIS II</libelleParc>
				<statusParc>LIBRE</statusParc>
				<placesLibresParc>21</placesLibresParc>
				<placesLibresUpdate>2019-01-01 05:33:43.76069</placesLibresUpdate>
				<presents>
					<presentsUpdate>2019-01-01 05:33:44.289516</presentsUpdate>
					<presentsTotal>83</presentsTotal>
					<presentsAbonnes>20</presentsAbonnes>
					<presentsHoraires>63</presentsHoraires>
				</presents>
			</Parc>
		</Quartier>
		<Quartier>
			<nomQuartier>la Condamine</nomQuartier>
			<totalLibresQuartier>759</totalLibresQuartier>
			<totalPresentsQuartier>736</totalPresentsQuartier>
			<totalPresentsHorairesQuartier>149</totalPresentsHorairesQuartier>
			<totalPresentsAbonnesQuartier>587</totalPresentsAbonnesQuartier>
			<Parc>
				<numParc>28</numParc>
				<libelleParc>CONDAMINE</libelleParc>
				<statusParc>LIBRE</statusParc>
				<placesLibresParc>180</placesLibresParc>
				<placesLibresUpdate>2019-01-01 05:33:43.909738</placesLibresUpdate>
				<presents>
					<presentsUpdate>2019-01-01 05:33:44.761011</presentsUpdate>
					<presentsTotal>186</presentsTotal>
					<presentsAbonnes>166</presentsAbonnes>
					<presentsHoraires>20</presentsHoraires>
				</presents>
			</Parc>
			<Parc>
				<numParc>31</numParc>
				<libelleParc>PLACE D ARMES</libelleParc>
				<statusParc>LIBRE</statusParc>
				<placesLibresParc>50</placesLibresParc>
				<placesLibresUpdate>2019-01-01 05:33:43.934896</placesLibresUpdate>
				<presents>
					<presentsUpdate>2019-01-01 05:33:44.786367</presentsUpdate>
					<presentsTotal>8</presentsTotal>
					<presentsAbonnes>0</presentsAbonnes>
					<presentsHoraires>8</presentsHoraires>
				</presents>
			</Parc>
			<Parc>
				<numParc>32</numParc>
				<libelleParc>QUAI ANTOINE 1ER</libelleParc>
				<statusParc>LIBRE</statusParc>
				<placesLibresParc>173</placesLibresParc>
				<placesLibresUpdate>2019-01-01 05:33:43.943424</placesLibresUpdate>
				<presents>
					<presentsUpdate>2019-01-01 05:33:44.794813</presentsUpdate>
					<presentsTotal>81</presentsTotal>
					<presentsAbonnes>39</presentsAbonnes>
					<presentsHoraires>42</presentsHoraires>
				</presents>
			</Parc>
			<Parc>
				<numParc>36</numParc>
				<libelleParc>SQUARE GASTAUD</libelleParc>
				<statusParc>LIBRE</statusParc>
				<placesLibresParc>115</placesLibresParc>
				<placesLibresUpdate>2019-01-01 05:33:43.968993</placesLibresUpdate>
				<presents>
					<presentsUpdate>2019-01-01 05:33:44.803185</presentsUpdate>
					<presentsTotal>125</presentsTotal>
					<presentsAbonnes>93</presentsAbonnes>
					<presentsHoraires>32</presentsHoraires>
				</presents>
			</Parc>
			<Parc>
				<numParc>39</numParc>
				<libelleParc>LES AGAVES</libelleParc>
				<statusParc>LIBRE</statusParc>
				<placesLibresParc>23</placesLibresParc>
				<placesLibresUpdate>2019-01-01 05:33:43.986293</placesLibresUpdate>
				<presents>
					<presentsUpdate>2019-01-01 05:33:44.526868</presentsUpdate>
					<presentsTotal>66</presentsTotal>
					<presentsAbonnes>59</presentsAbonnes>
					<presentsHoraires>7</presentsHoraires>
				</presents>
			</Parc>
			<Parc>
				<numParc>9</numParc>
				<libelleParc>LA COLLE</libelleParc>
				<statusParc>LIBRE</statusParc>
				<placesLibresParc>218</placesLibresParc>
				<placesLibresUpdate>2019-01-01 05:33:43.788633</placesLibresUpdate>
				<presents>
					<presentsUpdate>2019-01-01 05:33:44.677108</presentsUpdate>
					<presentsTotal>270</presentsTotal>
					<presentsAbonnes>230</presentsAbonnes>
					<presentsHoraires>40</presentsHoraires>
				</presents>
			</Parc>
		</Quartier>
	</Document>
