<?xml version="1.0" encoding="ISO-8859-1"?>
	<Document>
		<totalPresent>4693</totalPresent>
		<totalLibre>3609</totalLibre>
		<lastUpdate>mer., 23 janv. 2019 03:54:01 +0100</lastUpdate>
		<Quartier>
			<nomQuartier>Fontvieille</nomQuartier>
			<totalLibresQuartier>1068</totalLibresQuartier>
			<totalPresentsQuartier>1100</totalPresentsQuartier>
			<totalPresentsHorairesQuartier>620</totalPresentsHorairesQuartier>
			<totalPresentsAbonnesQuartier>480</totalPresentsAbonnesQuartier>
			<Parc>
				<numParc>124</numParc>
				<libelleParc>ECOLES RDC</libelleParc>
				<statusParc>LIBRE</statusParc>
				<placesLibresParc>59</placesLibresParc>
				<placesLibresUpdate>2019-01-23 03:52:40.022413</placesLibresUpdate>
				<presents>
					<presentsUpdate>2019-01-23 03:53:37.013671</presentsUpdate>
					<presentsTotal>14</presentsTotal>
					<presentsAbonnes>10</presentsAbonnes>
					<presentsHoraires>4</presentsHoraires>
				</presents>
			</Parc>
			<Parc>
				<numParc>13</numParc>
				<libelleParc>PAPALINS</libelleParc>
				<statusParc>LIBRE</statusParc>
				<placesLibresParc>27</placesLibresParc>
				<placesLibresUpdate>2019-01-23 03:52:39.752153</placesLibresUpdate>
				<presents>
					<presentsUpdate>2019-01-23 03:53:37.10626</presentsUpdate>
					<presentsTotal>38</presentsTotal>
					<presentsAbonnes>33</presentsAbonnes>
					<presentsHoraires>5</presentsHoraires>
				</presents>
			</Parc>
			<Parc>
				<numParc>14</numParc>
				<libelleParc>STADE</libelleParc>
				<statusParc>LIBRE</statusParc>
				<placesLibresParc>195</placesLibresParc>
				<placesLibresUpdate>2019-01-23 03:52:39.760671</placesLibresUpdate>
				<presents>
					<presentsUpdate>2019-01-23 03:53:36.827565</presentsUpdate>
					<presentsTotal>691</presentsTotal>
					<presentsAbonnes>123</presentsAbonnes>
					<presentsHoraires>568</presentsHoraires>
				</presents>
			</Parc>
			<Parc>
				<numParc>21</numParc>
				<libelleParc>PORT</libelleParc>
				<statusParc>LIBRE</statusParc>
				<placesLibresParc>76</placesLibresParc>
				<placesLibresUpdate>2019-01-23 03:52:39.803122</placesLibresUpdate>
				<presents>
					<presentsUpdate>2019-01-23 03:53:36.853055</presentsUpdate>
					<presentsTotal>99</presentsTotal>
					<presentsAbonnes>87</presentsAbonnes>
					<presentsHoraires>12</presentsHoraires>
				</presents>
			</Parc>
			<Parc>
				<numParc>24</numParc>
				<libelleParc>ECOLES</libelleParc>
				<statusParc>LIBRE</statusParc>
				<placesLibresParc>14</placesLibresParc>
				<placesLibresUpdate>2019-01-23 03:52:39.820018</placesLibresUpdate>
				<presents>
					<presentsUpdate>2019-01-23 03:53:36.861674</presentsUpdate>
					<presentsTotal>52</presentsTotal>
					<presentsAbonnes>52</presentsAbonnes>
					<presentsHoraires>0</presentsHoraires>
				</presents>
			</Parc>
			<Parc>
				<numParc>25</numParc>
				<libelleParc>ST NICOLAS</libelleParc>
				<statusParc>LIBRE</statusParc>
				<placesLibresParc>72</placesLibresParc>
				<placesLibresUpdate>2019-01-23 03:52:39.828609</placesLibresUpdate>
				<presents>
					<presentsUpdate>2019-01-23 03:53:36.870673</presentsUpdate>
					<presentsTotal>22</presentsTotal>
					<presentsAbonnes>12</presentsAbonnes>
					<presentsHoraires>10</presentsHoraires>
				</presents>
			</Parc>
			<Parc>
				<numParc>29</numParc>
				<libelleParc>HELIPORT</libelleParc>
				<statusParc>LIBRE</statusParc>
				<placesLibresParc>9</placesLibresParc>
				<placesLibresUpdate>2019-01-23 03:52:39.862624</placesLibresUpdate>
				<presents>
					<presentsUpdate>2019-01-23 03:53:36.887578</presentsUpdate>
					<presentsTotal>35</presentsTotal>
					<presentsAbonnes>24</presentsAbonnes>
					<presentsHoraires>11</presentsHoraires>
				</presents>
			</Parc>
			<Parc>
				<numParc>30</numParc>
				<libelleParc>C.C.F.</libelleParc>
				<statusParc>LIBRE</statusParc>
				<placesLibresParc>554</placesLibresParc>
				<placesLibresUpdate>2019-01-23 03:52:39.870898</placesLibresUpdate>
				<presents>
					<presentsUpdate>2019-01-23 03:53:36.896098</presentsUpdate>
					<presentsTotal>10</presentsTotal>
					<presentsAbonnes>6</presentsAbonnes>
					<presentsHoraires>4</presentsHoraires>
				</presents>
			</Parc>
			<Parc>
				<numParc>52</numParc>
				<libelleParc>ST ANTOINE</libelleParc>
				<statusParc>LIBRE</statusParc>
				<placesLibresParc>62</placesLibresParc>
				<placesLibresUpdate>2019-01-23 03:52:39.988356</placesLibresUpdate>
				<presents>
					<presentsUpdate>2019-01-23 03:53:36.938223</presentsUpdate>
					<presentsTotal>139</presentsTotal>
					<presentsAbonnes>133</presentsAbonnes>
					<presentsHoraires>6</presentsHoraires>
				</presents>
			</Parc>
		</Quartier>
		<Quartier>
			<nomQuartier>I-Cars</nomQuartier>
			<totalLibresQuartier>46</totalLibresQuartier>
			<totalPresentsQuartier>6</totalPresentsQuartier>
			<totalPresentsHorairesQuartier>2</totalPresentsHorairesQuartier>
			<totalPresentsAbonnesQuartier>4</totalPresentsAbonnesQuartier>
			<Parc>
				<numParc>104</numParc>
				<libelleParc>GRIMALDI FORUM BUS</libelleParc>
				<statusParc>LIBRE</statusParc>
				<placesLibresParc>21</placesLibresParc>
				<placesLibresUpdate>2019-01-23 03:52:40.005258</placesLibresUpdate>
				<presents>
					<presentsUpdate>2019-01-23 03:53:36.658213</presentsUpdate>
					<presentsTotal>5</presentsTotal>
					<presentsAbonnes>3</presentsAbonnes>
					<presentsHoraires>2</presentsHoraires>
				</presents>
			</Parc>
			<Parc>
				<numParc>112</numParc>
				<libelleParc>PECHEURS BUS</libelleParc>
				<statusParc>LIBRE</statusParc>
				<placesLibresParc>22</placesLibresParc>
				<placesLibresUpdate>2019-01-23 03:52:40.013929</placesLibresUpdate>
				<presents>
					<presentsUpdate>2019-01-23 03:53:36.979979</presentsUpdate>
					<presentsTotal>1</presentsTotal>
					<presentsAbonnes>1</presentsAbonnes>
					<presentsHoraires>0</presentsHoraires>
				</presents>
			</Parc>
			<Parc>
				<numParc>19</numParc>
				<libelleParc>REGULATION BUS</libelleParc>
				<statusParc>LIBRE</statusParc>
				<placesLibresParc>3</placesLibresParc>
				<placesLibresUpdate>2019-01-23 03:52:39.794626</placesLibresUpdate>
				<presents>
					<presentsUpdate>2010-04-16 09:17:37.639024</presentsUpdate>
					<presentsTotal>0</presentsTotal>
					<presentsAbonnes>Obsolete</presentsAbonnes>
					<presentsHoraires>Obsolete</presentsHoraires>
				</presents>
			</Parc>
		</Quartier>
		<Quartier>
			<nomQuartier>Jardin-Exotique</nomQuartier>
			<totalLibresQuartier>482</totalLibresQuartier>
			<totalPresentsQuartier>1003</totalPresentsQuartier>
			<totalPresentsHorairesQuartier>79</totalPresentsHorairesQuartier>
			<totalPresentsAbonnesQuartier>924</totalPresentsAbonnesQuartier>
			<Parc>
				<numParc>127</numParc>
				<libelleParc>CHPG 2 (BAS)</libelleParc>
				<statusParc>LIBRE</statusParc>
				<placesLibresParc>255</placesLibresParc>
				<placesLibresUpdate>2019-01-23 03:52:40.030822</placesLibresUpdate>
				<presents>
					<presentsUpdate>2019-01-23 03:53:36.708704</presentsUpdate>
					<presentsTotal>19</presentsTotal>
					<presentsAbonnes>0</presentsAbonnes>
					<presentsHoraires>19</presentsHoraires>
				</presents>
			</Parc>
			<Parc>
				<numParc>16</numParc>
				<libelleParc>JARDIN EXOTIQUE</libelleParc>
				<statusParc>LIBRE</statusParc>
				<placesLibresParc>48</placesLibresParc>
				<placesLibresUpdate>2019-01-23 03:52:39.77754</placesLibresUpdate>
				<presents>
					<presentsUpdate>2019-01-23 03:53:36.530869</presentsUpdate>
					<presentsTotal>347</presentsTotal>
					<presentsAbonnes>327</presentsAbonnes>
					<presentsHoraires>20</presentsHoraires>
				</presents>
			</Parc>
			<Parc>
				<numParc>27</numParc>
				<libelleParc>CHPG 1 (HAUT)</libelleParc>
				<statusParc>COMPLET</statusParc>
				<placesLibresParc>0</placesLibresParc>
				<placesLibresUpdate>2019-01-23 03:52:39.845586</placesLibresUpdate>
				<presents>
					<presentsUpdate>2019-01-23 03:53:36.556137</presentsUpdate>
					<presentsTotal>0</presentsTotal>
					<presentsAbonnes>28</presentsAbonnes>
					<presentsHoraires>0</presentsHoraires>
				</presents>
			</Parc>
			<Parc>
				<numParc>34</numParc>
				<libelleParc>GARE</libelleParc>
				<statusParc>LIBRE</statusParc>
				<placesLibresParc>51</placesLibresParc>
				<placesLibresUpdate>2019-01-23 03:52:39.904641</placesLibresUpdate>
				<presents>
					<presentsUpdate>2019-01-23 03:53:36.57335</presentsUpdate>
					<presentsTotal>560</presentsTotal>
					<presentsAbonnes>535</presentsAbonnes>
					<presentsHoraires>25</presentsHoraires>
				</presents>
			</Parc>
			<Parc>
				<numParc>45</numParc>
				<libelleParc>ATHENA</libelleParc>
				<statusParc>COMPLET</statusParc>
				<placesLibresParc>0</placesLibresParc>
				<placesLibresUpdate>2019-01-23 03:52:39.971791</placesLibresUpdate>
				<presents>
					<presentsUpdate>2019-01-23 03:53:36.632848</presentsUpdate>
					<presentsTotal>0</presentsTotal>
					<presentsAbonnes>15</presentsAbonnes>
					<presentsHoraires>0</presentsHoraires>
				</presents>
			</Parc>
			<Parc>
				<numParc>46</numParc>
				<libelleParc>DES OLIVIERS</libelleParc>
				<statusParc>LIBRE</statusParc>
				<placesLibresParc>22</placesLibresParc>
				<placesLibresUpdate>2019-01-23 03:52:39.980078</placesLibresUpdate>
				<presents>
					<presentsUpdate>2019-01-23 03:53:36.641399</presentsUpdate>
					<presentsTotal>5</presentsTotal>
					<presentsAbonnes>0</presentsAbonnes>
					<presentsHoraires>5</presentsHoraires>
				</presents>
			</Parc>
			<Parc>
				<numParc>60</numParc>
				<libelleParc>ENGELIN</libelleParc>
				<statusParc>LIBRE</statusParc>
				<placesLibresParc>92</placesLibresParc>
				<placesLibresUpdate>2019-01-23 03:52:39.996893</placesLibresUpdate>
				<presents>
					<presentsUpdate>2019-01-23 03:53:36.649756</presentsUpdate>
					<presentsTotal>36</presentsTotal>
					<presentsAbonnes>28</presentsAbonnes>
					<presentsHoraires>8</presentsHoraires>
				</presents>
			</Parc>
			<Parc>
				<numParc>7</numParc>
				<libelleParc>BOSIO</libelleParc>
				<statusParc>COMPLET</statusParc>
				<placesLibresParc>0</placesLibresParc>
				<placesLibresUpdate>2019-01-23 03:52:39.717865</placesLibresUpdate>
				<presents>
					<presentsUpdate>2019-01-23 03:53:36.50506</presentsUpdate>
					<presentsTotal>0</presentsTotal>
					<presentsAbonnes>295</presentsAbonnes>
					<presentsHoraires>21</presentsHoraires>
				</presents>
			</Parc>
			<Parc>
				<numParc>8</numParc>
				<libelleParc>PLATI</libelleParc>
				<statusParc>LIBRE</statusParc>
				<placesLibresParc>14</placesLibresParc>
				<placesLibresUpdate>2019-01-23 03:52:39.726532</placesLibresUpdate>
				<presents>
					<presentsUpdate>2019-01-23 03:53:36.513821</presentsUpdate>
					<presentsTotal>36</presentsTotal>
					<presentsAbonnes>34</presentsAbonnes>
					<presentsHoraires>2</presentsHoraires>
				</presents>
			</Parc>
		</Quartier>
		<Quartier>
			<nomQuartier>La Rousse</nomQuartier>
			<totalLibresQuartier>17</totalLibresQuartier>
			<totalPresentsQuartier>67</totalPresentsQuartier>
			<totalPresentsHorairesQuartier>4</totalPresentsHorairesQuartier>
			<totalPresentsAbonnesQuartier>63</totalPresentsAbonnesQuartier>
			<Parc>
				<numParc>5</numParc>
				<libelleParc>ANNONCIADE</libelleParc>
				<statusParc>LIBRE</statusParc>
				<placesLibresParc>17</placesLibresParc>
				<placesLibresUpdate>2019-01-23 03:52:39.701206</placesLibresUpdate>
				<presents>
					<presentsUpdate>2019-01-23 03:53:36.488076</presentsUpdate>
					<presentsTotal>67</presentsTotal>
					<presentsAbonnes>63</presentsAbonnes>
					<presentsHoraires>4</presentsHoraires>
				</presents>
			</Parc>
		</Quartier>
		<Quartier>
			<nomQuartier>Larvotto</nomQuartier>
			<totalLibresQuartier>417</totalLibresQuartier>
			<totalPresentsQuartier>395</totalPresentsQuartier>
			<totalPresentsHorairesQuartier>89</totalPresentsHorairesQuartier>
			<totalPresentsAbonnesQuartier>306</totalPresentsAbonnesQuartier>
			<Parc>
				<numParc>3</numParc>
				<libelleParc>LARVOTTO</libelleParc>
				<statusParc>LIBRE</statusParc>
				<placesLibresParc>127</placesLibresParc>
				<placesLibresUpdate>2019-01-23 03:52:39.684932</placesLibresUpdate>
				<presents>
					<presentsUpdate>2019-01-23 03:53:36.471247</presentsUpdate>
					<presentsTotal>133</presentsTotal>
					<presentsAbonnes>100</presentsAbonnes>
					<presentsHoraires>33</presentsHoraires>
				</presents>
			</Parc>
			<Parc>
				<numParc>38</numParc>
				<libelleParc>LES CARMES</libelleParc>
				<statusParc>COMPLET</statusParc>
				<placesLibresParc>0</placesLibresParc>
				<placesLibresUpdate>2019-01-23 03:52:39.921327</placesLibresUpdate>
				<presents>
					<presentsUpdate>2019-01-23 03:53:36.59031</presentsUpdate>
					<presentsTotal>0</presentsTotal>
					<presentsAbonnes>40</presentsAbonnes>
					<presentsHoraires>2</presentsHoraires>
				</presents>
			</Parc>
			<Parc>
				<numParc>4</numParc>
				<libelleParc>GRIMALDI FORUM</libelleParc>
				<statusParc>LIBRE</statusParc>
				<placesLibresParc>254</placesLibresParc>
				<placesLibresUpdate>2019-01-23 03:52:39.692359</placesLibresUpdate>
				<presents>
					<presentsUpdate>2019-01-23 03:53:36.479735</presentsUpdate>
					<presentsTotal>209</presentsTotal>
					<presentsAbonnes>163</presentsAbonnes>
					<presentsHoraires>46</presentsHoraires>
				</presents>
			</Parc>
			<Parc>
				<numParc>43</numParc>
				<libelleParc>TESTIMONIO</libelleParc>
				<statusParc>LIBRE</statusParc>
				<placesLibresParc>36</placesLibresParc>
				<placesLibresUpdate>2019-01-23 03:52:39.954973</placesLibresUpdate>
				<presents>
					<presentsUpdate>2019-01-23 03:53:36.61585</presentsUpdate>
					<presentsTotal>53</presentsTotal>
					<presentsAbonnes>43</presentsAbonnes>
					<presentsHoraires>10</presentsHoraires>
				</presents>
			</Parc>
		</Quartier>
		<Quartier>
			<nomQuartier>Le Rocher</nomQuartier>
			<totalLibresQuartier>326</totalLibresQuartier>
			<totalPresentsQuartier>370</totalPresentsQuartier>
			<totalPresentsHorairesQuartier>48</totalPresentsHorairesQuartier>
			<totalPresentsAbonnesQuartier>322</totalPresentsAbonnesQuartier>
			<Parc>
				<numParc>12</numParc>
				<libelleParc>PECHEURS</libelleParc>
				<statusParc>LIBRE</statusParc>
				<placesLibresParc>251</placesLibresParc>
				<placesLibresUpdate>2019-01-23 03:52:39.743447</placesLibresUpdate>
				<presents>
					<presentsUpdate>2019-01-23 03:53:36.818959</presentsUpdate>
					<presentsTotal>151</presentsTotal>
					<presentsAbonnes>146</presentsAbonnes>
					<presentsHoraires>5</presentsHoraires>
				</presents>
			</Parc>
			<Parc>
				<numParc>17</numParc>
				<libelleParc>ABBAYE</libelleParc>
				<statusParc>LIBRE</statusParc>
				<placesLibresParc>13</placesLibresParc>
				<placesLibresUpdate>2019-01-23 03:52:39.786215</placesLibresUpdate>
				<presents>
					<presentsUpdate>2019-01-23 03:53:36.836038</presentsUpdate>
					<presentsTotal>20</presentsTotal>
					<presentsAbonnes>7</presentsAbonnes>
					<presentsHoraires>13</presentsHoraires>
				</presents>
			</Parc>
			<Parc>
				<numParc>2</numParc>
				<libelleParc>VISITATION</libelleParc>
				<statusParc>LIBRE</statusParc>
				<placesLibresParc>16</placesLibresParc>
				<placesLibresUpdate>2019-01-23 03:52:39.675479</placesLibresUpdate>
				<presents>
					<presentsUpdate>2019-01-23 03:53:36.784993</presentsUpdate>
					<presentsTotal>13</presentsTotal>
					<presentsAbonnes>11</presentsAbonnes>
					<presentsHoraires>2</presentsHoraires>
				</presents>
			</Parc>
			<Parc>
				<numParc>41</numParc>
				<libelleParc>LA DIGUE</libelleParc>
				<statusParc>LIBRE</statusParc>
				<placesLibresParc>46</placesLibresParc>
				<placesLibresUpdate>2019-01-23 03:52:39.937952</placesLibresUpdate>
				<presents>
					<presentsUpdate>2019-01-23 03:53:36.929831</presentsUpdate>
					<presentsTotal>186</presentsTotal>
					<presentsAbonnes>158</presentsAbonnes>
					<presentsHoraires>28</presentsHoraires>
				</presents>
			</Parc>
		</Quartier>
		<Quartier>
			<nomQuartier>Monte-Carlo</nomQuartier>
			<totalLibresQuartier>857</totalLibresQuartier>
			<totalPresentsQuartier>1001</totalPresentsQuartier>
			<totalPresentsHorairesQuartier>163</totalPresentsHorairesQuartier>
			<totalPresentsAbonnesQuartier>838</totalPresentsAbonnesQuartier>
			<Parc>
				<numParc>1</numParc>
				<libelleParc>MOULINS</libelleParc>
				<statusParc>LIBRE</statusParc>
				<placesLibresParc>88</placesLibresParc>
				<placesLibresUpdate>2019-01-23 03:52:39.666929</placesLibresUpdate>
				<presents>
					<presentsUpdate>2019-01-23 03:53:36.462975</presentsUpdate>
					<presentsTotal>215</presentsTotal>
					<presentsAbonnes>150</presentsAbonnes>
					<presentsHoraires>65</presentsHoraires>
				</presents>
			</Parc>
			<Parc>
				<numParc>15</numParc>
				<libelleParc>COSTA</libelleParc>
				<statusParc>LIBRE</statusParc>
				<placesLibresParc>17</placesLibresParc>
				<placesLibresUpdate>2019-01-23 03:52:39.769039</placesLibresUpdate>
				<presents>
					<presentsUpdate>2019-01-23 03:53:36.522209</presentsUpdate>
					<presentsTotal>125</presentsTotal>
					<presentsAbonnes>124</presentsAbonnes>
					<presentsHoraires>1</presentsHoraires>
				</presents>
			</Parc>
			<Parc>
				<numParc>22</numParc>
				<libelleParc>CASINO</libelleParc>
				<statusParc>LIBRE</statusParc>
				<placesLibresParc>341</placesLibresParc>
				<placesLibresUpdate>2019-01-23 03:52:39.811581</placesLibresUpdate>
				<presents>
					<presentsUpdate>2019-01-23 03:53:36.539142</presentsUpdate>
					<presentsTotal>126</presentsTotal>
					<presentsAbonnes>85</presentsAbonnes>
					<presentsHoraires>41</presentsHoraires>
				</presents>
			</Parc>
			<Parc>
				<numParc>26</numParc>
				<libelleParc>ST CHARLES</libelleParc>
				<statusParc>LIBRE</statusParc>
				<placesLibresParc>147</placesLibresParc>
				<placesLibresUpdate>2019-01-23 03:52:39.837078</placesLibresUpdate>
				<presents>
					<presentsUpdate>2019-01-23 03:53:36.547618</presentsUpdate>
					<presentsTotal>189</presentsTotal>
					<presentsAbonnes>181</presentsAbonnes>
					<presentsHoraires>8</presentsHoraires>
				</presents>
			</Parc>
			<Parc>
				<numParc>33</numParc>
				<libelleParc>ST LAURENT</libelleParc>
				<statusParc>LIBRE</statusParc>
				<placesLibresParc>63</placesLibresParc>
				<placesLibresUpdate>2019-01-23 03:52:39.896026</placesLibresUpdate>
				<presents>
					<presentsUpdate>2019-01-23 03:53:36.564805</presentsUpdate>
					<presentsTotal>107</presentsTotal>
					<presentsAbonnes>100</presentsAbonnes>
					<presentsHoraires>7</presentsHoraires>
				</presents>
			</Parc>
			<Parc>
				<numParc>42</numParc>
				<libelleParc>OSTENDE</libelleParc>
				<statusParc>LIBRE</statusParc>
				<placesLibresParc>65</placesLibresParc>
				<placesLibresUpdate>2019-01-23 03:52:39.94639</placesLibresUpdate>
				<presents>
					<presentsUpdate>2019-01-23 03:53:36.607328</presentsUpdate>
					<presentsTotal>46</presentsTotal>
					<presentsAbonnes>30</presentsAbonnes>
					<presentsHoraires>16</presentsHoraires>
				</presents>
			</Parc>
			<Parc>
				<numParc>44</numParc>
				<libelleParc>ROQUEVILLE</libelleParc>
				<statusParc>LIBRE</statusParc>
				<placesLibresParc>67</placesLibresParc>
				<placesLibresUpdate>2019-01-23 03:52:39.96316</placesLibresUpdate>
				<presents>
					<presentsUpdate>2019-01-23 03:53:36.62443</presentsUpdate>
					<presentsTotal>185</presentsTotal>
					<presentsAbonnes>167</presentsAbonnes>
					<presentsHoraires>18</presentsHoraires>
				</presents>
			</Parc>
			<Parc>
				<numParc>6</numParc>
				<libelleParc>LOUIS II</libelleParc>
				<statusParc>LIBRE</statusParc>
				<placesLibresParc>69</placesLibresParc>
				<placesLibresUpdate>2019-01-23 03:52:39.709574</placesLibresUpdate>
				<presents>
					<presentsUpdate>2019-01-23 03:53:36.496804</presentsUpdate>
					<presentsTotal>8</presentsTotal>
					<presentsAbonnes>1</presentsAbonnes>
					<presentsHoraires>7</presentsHoraires>
				</presents>
			</Parc>
		</Quartier>
		<Quartier>
			<nomQuartier>la Condamine</nomQuartier>
			<totalLibresQuartier>396</totalLibresQuartier>
			<totalPresentsQuartier>751</totalPresentsQuartier>
			<totalPresentsHorairesQuartier>69</totalPresentsHorairesQuartier>
			<totalPresentsAbonnesQuartier>682</totalPresentsAbonnesQuartier>
			<Parc>
				<numParc>28</numParc>
				<libelleParc>CONDAMINE</libelleParc>
				<statusParc>LIBRE</statusParc>
				<placesLibresParc>76</placesLibresParc>
				<placesLibresUpdate>2019-01-23 03:52:39.853994</placesLibresUpdate>
				<presents>
					<presentsUpdate>2019-01-23 03:53:36.879326</presentsUpdate>
					<presentsTotal>193</presentsTotal>
					<presentsAbonnes>186</presentsAbonnes>
					<presentsHoraires>7</presentsHoraires>
				</presents>
			</Parc>
			<Parc>
				<numParc>31</numParc>
				<libelleParc>PLACE D ARMES</libelleParc>
				<statusParc>LIBRE</statusParc>
				<placesLibresParc>50</placesLibresParc>
				<placesLibresUpdate>2019-01-23 03:52:39.87916</placesLibresUpdate>
				<presents>
					<presentsUpdate>2019-01-23 03:53:36.904484</presentsUpdate>
					<presentsTotal>6</presentsTotal>
					<presentsAbonnes>0</presentsAbonnes>
					<presentsHoraires>6</presentsHoraires>
				</presents>
			</Parc>
			<Parc>
				<numParc>32</numParc>
				<libelleParc>QUAI ANTOINE 1ER</libelleParc>
				<statusParc>LIBRE</statusParc>
				<placesLibresParc>110</placesLibresParc>
				<placesLibresUpdate>2019-01-23 03:52:39.887763</placesLibresUpdate>
				<presents>
					<presentsUpdate>2019-01-23 03:53:36.912874</presentsUpdate>
					<presentsTotal>47</presentsTotal>
					<presentsAbonnes>33</presentsAbonnes>
					<presentsHoraires>14</presentsHoraires>
				</presents>
			</Parc>
			<Parc>
				<numParc>36</numParc>
				<libelleParc>SQUARE GASTAUD</libelleParc>
				<statusParc>LIBRE</statusParc>
				<placesLibresParc>89</placesLibresParc>
				<placesLibresUpdate>2019-01-23 03:52:39.912866</placesLibresUpdate>
				<presents>
					<presentsUpdate>2019-01-23 03:53:36.921264</presentsUpdate>
					<presentsTotal>127</presentsTotal>
					<presentsAbonnes>120</presentsAbonnes>
					<presentsHoraires>7</presentsHoraires>
				</presents>
			</Parc>
			<Parc>
				<numParc>39</numParc>
				<libelleParc>LES AGAVES</libelleParc>
				<statusParc>LIBRE</statusParc>
				<placesLibresParc>17</placesLibresParc>
				<placesLibresUpdate>2019-01-23 03:52:39.929805</placesLibresUpdate>
				<presents>
					<presentsUpdate>2019-01-23 03:53:36.598882</presentsUpdate>
					<presentsTotal>74</presentsTotal>
					<presentsAbonnes>71</presentsAbonnes>
					<presentsHoraires>3</presentsHoraires>
				</presents>
			</Parc>
			<Parc>
				<numParc>9</numParc>
				<libelleParc>LA COLLE</libelleParc>
				<statusParc>LIBRE</statusParc>
				<placesLibresParc>54</placesLibresParc>
				<placesLibresUpdate>2019-01-23 03:52:39.734993</placesLibresUpdate>
				<presents>
					<presentsUpdate>2019-01-23 03:53:36.793423</presentsUpdate>
					<presentsTotal>304</presentsTotal>
					<presentsAbonnes>272</presentsAbonnes>
					<presentsHoraires>32</presentsHoraires>
				</presents>
			</Parc>
		</Quartier>
	</Document>
